{"assets":{"E891BCE4F9494B7916B360BB6F38F268":{"type":"texture","assetRequest":{"type":"slide","state":"incoming"},"url":"assets/E891BCE4F9494B7916B360BB6F38F268.svg","width":1024,"height":768},"CD0B86A8E7B4B659E85CE3274C990B92":{"type":"texture","assetRequest":{"type":"slide","state":"outgoing"},"url":"assets/CD0B86A8E7B4B659E85CE3274C990B92.svg","width":1024,"height":768}},"events":[{"effects":[{"beginTime":0,"baseLayer":{"animations":[],"initialState":{"affineTransform":[1,0,0,1,0,0],"masksToBounds":true,"rotation":0,"scale":1,"position":{"pointX":512,"pointY":384},"width":1024,"sublayerTransform":[1,0,0,0,0,1,0,0,0,0,1,0,0,0,0,1],"contentsRect":{"y":0,"x":0,"width":1,"height":1},"opacity":1,"edgeAntialiasingMask":0,"height":768,"hidden":false,"anchorPoint":{"pointX":0.5,"pointY":0.5}},"objectID":0,"layers":[{"animations":[],"initialState":{"affineTransform":[1,0,0,1,0,0],"masksToBounds":false,"rotation":0,"scale":1,"position":{"pointX":512,"pointY":384},"width":1024,"sublayerTransform":[1,0,0,0,0,1,0,0,0,0,1,-0.0004922987690640373,0,0,0,1],"contentsRect":{"y":0,"x":0,"width":1,"height":1},"opacity":1,"edgeAntialiasingMask":15,"height":768,"hidden":false,"anchorPoint":{"pointX":0.5,"pointY":0.5}},"layers":[{"animations":[],"layers":[],"initialState":{"affineTransform":[1,0,0,1,0,0],"masksToBounds":false,"rotation":0,"scale":1,"position":{"pointX":512,"pointY":384},"width":1024,"sublayerTransform":[1,0,0,0,0,1,0,0,0,0,1,0,0,0,0,1],"contentsRect":{"y":0,"x":0,"width":1,"height":1},"opacity":1,"edgeAntialiasingMask":0,"height":768,"hidden":false,"anchorPoint":{"pointX":0.5,"pointY":0.5}},"texture":"E891BCE4F9494B7916B360BB6F38F268"},{"animations":[{"from":{"scalar":false},"property":"hidden","beginTime":0,"to":{"scalar":true},"fillMode":"both","duration":0.01}],"layers":[],"initialState":{"affineTransform":[1,0,0,1,0,0],"masksToBounds":false,"rotation":0,"scale":1,"position":{"pointX":512,"pointY":384},"width":1024,"sublayerTransform":[1,0,0,0,0,1,0,0,0,0,1,0,0,0,0,1],"contentsRect":{"y":0,"x":0,"width":1,"height":1},"opacity":1,"edgeAntialiasingMask":0,"height":768,"hidden":false,"anchorPoint":{"pointX":0.5,"pointY":0.5}},"texture":"CD0B86A8E7B4B659E85CE3274C990B92"}]}]},"effects":[],"duration":0.01,"type":"transition","name":"none","objectID":0}],"automaticPlay":false,"hyperlinks":[],"accessibility":[{"text":"trait AdditivePriorityQueue[T] {","targetRectangle":{"y":-124.4990129470825,"x":14.61718368530273,"width":230.4375,"height":14.998046875}},{"text":"  def enqueue(value : T)(implicit valueTransformer: NodeContext[T] => T) : Unit","targetRectangle":{"y":-108.4990129470825,"x":14.61718368530273,"width":568.892578125,"height":14.998046875}},{"text":"  def find(guard : T => Boolean) : Option[T]","targetRectangle":{"y":-92.49901294708252,"x":14.61718368530273,"width":316.8515625,"height":14.998046875}},{"text":"  val topIsMinimum : Boolean","targetRectangle":{"y":-76.49901294708252,"x":14.61718368530273,"width":201.6328125,"height":14.998046875}},{"text":"}","targetRectangle":{"y":-60.49901294708252,"x":14.61718368530273,"width":7.201171875,"height":14.998046875}},{"text":"case class NodeContext[T](value : T, leftValue : Option[T], rightValue : Option[T])","targetRectangle":{"y":-44.49901294708252,"x":14.61718368530273,"width":597.697265625,"height":14.998046875}},{"text":"trait SparseMultiBoolean {","targetRectangle":{"y":3.50098705291748,"x":14.61718368530273,"width":187.23046875,"height":14.998046875}},{"text":"  type Q = AdditivePriorityQueue[Bound]","targetRectangle":{"y":19.50098705291748,"x":14.61718368530273,"width":280.845703125,"height":14.998046875}},{"text":"  case class Bound(value : Int, overlapCounter : Int)","targetRectangle":{"y":35.50098705291748,"x":14.61718368530273,"width":381.662109375,"height":14.998046875}},{"text":"  val emptyBound = Bound(0, 0)","targetRectangle":{"y":51.50098705291748,"x":14.61718368530273,"width":216.03515625,"height":14.998046875}},{"text":"  protected val toggleLowerBoundPlus : Q","targetRectangle":{"y":83.50098705291748,"x":14.61718368530273,"width":288.046875,"height":14.998046875}},{"text":"  protected val toggleUpperBoundMinus : Q","targetRectangle":{"y":99.50098705291748,"x":14.61718368530273,"width":295.248046875,"height":14.998046875}},{"text":"  def ?(i : Int) = isTrue(i)","targetRectangle":{"y":131.5009870529175,"x":14.61718368530273,"width":201.6328125,"height":14.998046875}},{"text":"  def isTrue(i : Int) : Boolean = {","targetRectangle":{"y":163.5009870529175,"x":14.61718368530273,"width":252.041015625,"height":14.998046875}},{"text":"    case class Test(queue : Q, findBy : Bound => Boolean)","targetRectangle":{"y":179.5009870529175,"x":14.61718368530273,"width":410.466796875,"height":14.998046875}},{"text":"    val counts = Seq(Test(toggleLowerBoundPlus, _.value <= i),","targetRectangle":{"y":195.5009870529175,"x":14.61718368530273,"width":446.47265625,"height":14.998046875}},{"text":"      Test(toggleUpperBoundMinus, _.value >= i)).map {","targetRectangle":{"y":211.5009870529175,"x":14.61718368530273,"width":388.86328125,"height":14.998046875}},{"text":"      case test => test.queue.find(test.findBy) match {","targetRectangle":{"y":227.5009870529175,"x":14.61718368530273,"width":396.064453125,"height":14.998046875}},{"text":"        case None => 0","targetRectangle":{"y":243.5009870529175,"x":14.61718368530273,"width":158.42578125,"height":14.998046875}},{"text":"        case Some(node) => node.overlapCounter","targetRectangle":{"y":259.5009870529175,"x":14.61718368530273,"width":331.25390625,"height":14.998046875}},{"text":"      }","targetRectangle":{"y":275.5009870529175,"x":14.61718368530273,"width":50.408203125,"height":14.998046875}},{"text":"    }","targetRectangle":{"y":291.5009870529175,"x":14.61718368530273,"width":36.005859375,"height":14.998046875}},{"text":"    math.min(counts(0), counts(1)) % 2 match {","targetRectangle":{"y":323.5009870529175,"x":14.61718368530273,"width":331.25390625,"height":14.998046875}},{"text":"      case 1 => true","targetRectangle":{"y":339.5009870529175,"x":14.61718368530273,"width":144.0234375,"height":14.998046875}},{"text":"      case 0 => false","targetRectangle":{"y":355.5009870529175,"x":14.61718368530273,"width":151.224609375,"height":14.998046875}},{"text":"    }","targetRectangle":{"y":371.5009870529175,"x":14.61718368530273,"width":36.005859375,"height":14.998046875}},{"text":"  }","targetRectangle":{"y":387.5009870529175,"x":14.61718368530273,"width":21.603515625,"height":14.998046875}},{"text":"  def toggle(i : Int, j : Int) : Unit = {","targetRectangle":{"y":419.5009870529175,"x":14.61718368530273,"width":295.248046875,"height":14.998046875}},{"text":"    implicit val transform : NodeContext[Bound] => Bound = (c : NodeContext[Bound]) => c match { case NodeContext(node, leftChild, rightChild) =>","targetRectangle":{"y":435.5009870529175,"x":14.61718368530273,"width":1044.169921875,"height":14.998046875}},{"text":"      Bound(node.value, leftChild.getOrElse(emptyBound).overlapCounter + rightChild.getOrElse(emptyBound).overlapCounter + 1)","targetRectangle":{"y":451.5009870529175,"x":14.61718368530273,"width":900.146484375,"height":14.998046875}},{"text":"    }","targetRectangle":{"y":467.5009870529175,"x":14.61718368530273,"width":36.005859375,"height":14.998046875}},{"text":"    toggleLowerBoundPlus enqueue Bound(i, 0)","targetRectangle":{"y":499.5009870529175,"x":14.61718368530273,"width":316.8515625,"height":14.998046875}},{"text":"    toggleUpperBoundMinus enqueue Bound(j, 0)","targetRectangle":{"y":515.5009870529175,"x":14.61718368530273,"width":324.052734375,"height":14.998046875}},{"text":"  }","targetRectangle":{"y":531.5009870529175,"x":14.61718368530273,"width":21.603515625,"height":14.998046875}},{"text":"}","targetRectangle":{"y":547.5009870529175,"x":14.61718368530273,"width":7.201171875,"height":14.998046875}},{"text":"netflix-logo.gif","targetRectangle":{"y":649.62353515625,"x":705.8783569335938,"width":86.22567749023438,"height":40}},{"text":"twitter.png","targetRectangle":{"y":706.2470703125,"x":832.6953125,"width":32.80183029174805,"height":32.80183029174805}},{"text":"Ryan Delucchi","targetRectangle":{"y":653.62353515625,"x":803.3037719726562,"width":167.102,"height":31.27200317382812}},{"text":"Scala: Elégant by design","targetRectangle":{"y":649,"x":84.37897705078126,"width":476.01,"height":53.69468688964844}},{"text":"EPFL.jpg","targetRectangle":{"y":-140,"x":-16.5,"width":1046,"height":768}},{"text":"@ryanonsrc","targetRectangle":{"y":711.6480102539062,"x":867.953857421875,"width":104.16,"height":23.44000244140625}}],"baseLayer":{"animations":[],"initialState":{"affineTransform":[1,0,0,1,0,0],"masksToBounds":true,"rotation":0,"scale":1,"position":{"pointX":512,"pointY":384},"width":1024,"sublayerTransform":[1,0,0,0,0,1,0,0,0,0,1,0,0,0,0,1],"contentsRect":{"y":0,"x":0,"width":1,"height":1},"opacity":1,"edgeAntialiasingMask":0,"height":768,"hidden":false,"anchorPoint":{"pointX":0.5,"pointY":0.5}},"objectID":0,"layers":[{"animations":[],"initialState":{"affineTransform":[1,0,0,1,0,0],"masksToBounds":false,"rotation":0,"scale":1,"position":{"pointX":512,"pointY":384},"width":1024,"sublayerTransform":[1,0,0,0,0,1,0,0,0,0,1,-0.0004922987690640373,0,0,0,1],"contentsRect":{"y":0,"x":0,"width":1,"height":1},"opacity":1,"edgeAntialiasingMask":15,"height":768,"hidden":false,"anchorPoint":{"pointX":0.5,"pointY":0.5}},"layers":[{"animations":[],"layers":[],"initialState":{"affineTransform":[1,0,0,1,0,0],"masksToBounds":false,"rotation":0,"scale":1,"position":{"pointX":512,"pointY":384},"width":1024,"sublayerTransform":[1,0,0,0,0,1,0,0,0,0,1,0,0,0,0,1],"contentsRect":{"y":0,"x":0,"width":1,"height":1},"opacity":1,"edgeAntialiasingMask":0,"height":768,"hidden":false,"anchorPoint":{"pointX":0.5,"pointY":0.5}},"texture":"E891BCE4F9494B7916B360BB6F38F268"},{"animations":[{"from":{"scalar":false},"property":"hidden","beginTime":0,"to":{"scalar":true},"fillMode":"both","duration":0.01}],"layers":[],"initialState":{"affineTransform":[1,0,0,1,0,0],"masksToBounds":false,"rotation":0,"scale":1,"position":{"pointX":512,"pointY":384},"width":1024,"sublayerTransform":[1,0,0,0,0,1,0,0,0,0,1,0,0,0,0,1],"contentsRect":{"y":0,"x":0,"width":1,"height":1},"opacity":1,"edgeAntialiasingMask":0,"height":768,"hidden":false,"anchorPoint":{"pointX":0.5,"pointY":0.5}},"texture":"CD0B86A8E7B4B659E85CE3274C990B92"}]}]}}]}