{"assets":{"55F4842570F5273DFF7CDA9C7FC58DD2":{"type":"texture","assetRequest":{"type":"slide","state":"contents"},"url":"assets/55F4842570F5273DFF7CDA9C7FC58DD2.svg","width":421,"height":224},"5BBC8E21AC430EC8AE55EF4FC9B26599":{"type":"texture","assetRequest":{"type":"slide","state":"incoming"},"url":"assets/5BBC8E21AC430EC8AE55EF4FC9B26599.svg","width":1024,"height":768},"970B8524056A785FC4EDB720A2EE594A":{"type":"texture","assetRequest":{"type":"slide","state":"contents"},"url":"assets/970B8524056A785FC4EDB720A2EE594A.svg","width":432,"height":381},"D2A07172630096E6CC3E98E6E3AEDBF7":{"type":"texture","assetRequest":{"type":"slide","state":"contents"},"url":"assets/D2A07172630096E6CC3E98E6E3AEDBF7.svg","width":780,"height":157},"AD4AE3662AEBEA73F5A2865D3DDEB497":{"type":"texture","assetRequest":{"type":"slide","state":"contents"},"url":"assets/AD4AE3662AEBEA73F5A2865D3DDEB497.svg","width":358,"height":81},"498E23C82CA78A4BCD7BA88E5243B6FC":{"type":"texture","assetRequest":{"type":"slide","state":"contents"},"url":"assets/498E23C82CA78A4BCD7BA88E5243B6FC.svg","width":1024,"height":768},"AF9DC6231E46CF01E2C59626D16E1D20":{"type":"texture","assetRequest":{"type":"slide","state":"contents"},"url":"assets/AF9DC6231E46CF01E2C59626D16E1D20.svg","width":300,"height":215},"479D3FD81573DCACFC9C4BFFAFEEF9DF":{"type":"texture","assetRequest":{"type":"slide","state":"contents"},"url":"assets/479D3FD81573DCACFC9C4BFFAFEEF9DF.svg","width":40,"height":52},"A3B5BAB2EB9DCC9F5C1592A17DE965BA":{"type":"texture","assetRequest":{"type":"slide","state":"contents"},"url":"assets/A3B5BAB2EB9DCC9F5C1592A17DE965BA.svg","width":211,"height":30},"7197DE062BC82A94A5A6253FFB6EE085":{"type":"texture","assetRequest":{"type":"slide","state":"contents"},"url":"assets/7197DE062BC82A94A5A6253FFB6EE085.svg","width":20,"height":86},"744191A6EC4A2A68A4771BC4C40BACFE":{"type":"texture","assetRequest":{"type":"slide","state":"contents"},"url":"assets/744191A6EC4A2A68A4771BC4C40BACFE.svg","width":863,"height":43},"4055A0845993B381E0E64EA4B82BF601":{"type":"texture","assetRequest":{"type":"slide","state":"outgoing"},"url":"assets/4055A0845993B381E0E64EA4B82BF601.svg","width":1024,"height":768},"DB106BF7A41AF014B1FD3566B1DBC04C":{"type":"texture","assetRequest":{"type":"slide","state":"contents"},"url":"assets/DB106BF7A41AF014B1FD3566B1DBC04C.svg","width":86,"height":34}},"events":[{"effects":[{"beginTime":0,"baseLayer":{"animations":[],"initialState":{"affineTransform":[1,0,0,1,0,0],"masksToBounds":false,"rotation":0,"scale":1,"position":{"pointX":522.9108123779297,"pointY":572.216705083847},"width":938.3867263793945,"sublayerTransform":[1,0,0,0,0,1,0,0,0,0,1,0,0,0,0,1],"contentsRect":{"y":0,"x":0,"width":1,"height":1},"opacity":1,"edgeAntialiasingMask":15,"height":163.1922602653503,"hidden":false,"anchorPoint":{"pointX":0.5,"pointY":0.5}},"objectID":0,"layers":[{"animations":[],"initialState":{"affineTransform":[1,0,0,1,0,0],"masksToBounds":false,"rotation":0,"scale":1,"position":{"pointX":458.2825508117676,"pointY":-106.6205749511719},"width":938.3867263793945,"sublayerTransform":[1,0,0,0,0,1,0,0,0,0,1,-0.0004922987690640373,0,0,0,1],"contentsRect":{"y":0,"x":0,"width":1,"height":1},"opacity":1,"edgeAntialiasingMask":15,"height":163.1922602653503,"hidden":false,"anchorPoint":{"pointX":0.4883727976204148,"pointY":-0.6533433312205309}},"layers":[{"animations":[{"from":{"scalar":true},"property":"hidden","beginTime":1e-100,"to":{"scalar":false},"fillMode":"both","duration":0.01}],"layers":[],"initialState":{"affineTransform":[1,0,0,1,0,0],"masksToBounds":false,"rotation":0,"scale":1,"position":{"pointX":435.7825508117676,"pointY":27.87942504882812},"width":863,"sublayerTransform":[1,0,0,0,0,1,0,0,0,0,1,0,0,0,0,1],"contentsRect":{"y":0,"x":0,"width":1,"height":1},"opacity":1,"edgeAntialiasingMask":0,"height":43,"hidden":true,"anchorPoint":{"pointX":0.5,"pointY":0.5}},"texture":"744191A6EC4A2A68A4771BC4C40BACFE"}]}]},"effects":[],"duration":0.01,"type":"buildIn","name":"apple:appear","objectID":0},{"beginTime":0,"baseLayer":{"animations":[],"initialState":{"affineTransform":[1,0,0,1,0,0],"masksToBounds":false,"rotation":0,"scale":1,"position":{"pointX":627.1002459526062,"pointY":554.2884517908096},"width":255.4843664169312,"sublayerTransform":[1,0,0,0,0,1,0,0,0,0,1,0,0,0,0,1],"contentsRect":{"y":0,"x":0,"width":1,"height":1},"opacity":1,"edgeAntialiasingMask":15,"height":83.46484303474426,"hidden":false,"anchorPoint":{"pointX":0.5,"pointY":0.5}},"objectID":1,"layers":[{"animations":[],"initialState":{"affineTransform":[1,0,0,1,0,0],"masksToBounds":false,"rotation":0,"scale":1,"position":{"pointX":12.64193725585938,"pointY":-128.5560302734375},"width":255.4843664169312,"sublayerTransform":[1,0,0,0,0,1,0,0,0,0,1,-0.0004922987690640373,0,0,0,1],"contentsRect":{"y":0,"x":0,"width":1,"height":1},"opacity":1,"edgeAntialiasingMask":15,"height":83.46484303474426,"hidden":false,"anchorPoint":{"pointX":0.04948223420930849,"pointY":-1.540241682595904}},"layers":[{"animations":[{"from":{"scalar":true},"property":"hidden","beginTime":1e-100,"to":{"scalar":false},"fillMode":"both","duration":0.01}],"layers":[],"initialState":{"affineTransform":[1,0,0,1,0,0],"masksToBounds":false,"rotation":0,"scale":1,"position":{"pointX":108.1419372558594,"pointY":59.4439697265625},"width":211,"sublayerTransform":[1,0,0,0,0,1,0,0,0,0,1,0,0,0,0,1],"contentsRect":{"y":0,"x":0,"width":1,"height":1},"opacity":1,"edgeAntialiasingMask":0,"height":30,"hidden":true,"anchorPoint":{"pointX":0.5,"pointY":0.5}},"texture":"A3B5BAB2EB9DCC9F5C1592A17DE965BA"}]}]},"effects":[],"duration":0.01,"type":"buildIn","name":"apple:appear","objectID":1},{"beginTime":0,"baseLayer":{"animations":[],"initialState":{"affineTransform":[1,0,0,1,0,0],"masksToBounds":false,"rotation":0,"scale":1,"position":{"pointX":627.1002520056463,"pointY":544.3840942382812},"width":536.7005650464489,"sublayerTransform":[1,0,0,0,0,1,0,0,0,0,1,0,0,0,0,1],"contentsRect":{"y":0,"x":0,"width":1,"height":1},"opacity":1,"edgeAntialiasingMask":15,"height":4,"hidden":false,"anchorPoint":{"pointX":0.5,"pointY":0.5}},"objectID":2,"layers":[{"animations":[],"initialState":{"affineTransform":[1,0,0,1,0,0],"masksToBounds":false,"rotation":0,"scale":1,"position":{"pointX":153.2500305175781,"pointY":-158.3840942382812},"width":536.7005650464489,"sublayerTransform":[1,0,0,0,0,1,0,0,0,0,1,-0.0004922987690640373,0,0,0,1],"contentsRect":{"y":0,"x":0,"width":1,"height":1},"opacity":1,"edgeAntialiasingMask":15,"height":4,"hidden":false,"anchorPoint":{"pointX":0.2855410269678308,"pointY":-39.59602355957031}},"layers":[{"animations":[{"from":{"scalar":true},"property":"hidden","beginTime":1e-100,"to":{"scalar":false},"fillMode":"both","duration":0.01}],"layers":[],"initialState":{"affineTransform":[1,0,0,1,0,0],"masksToBounds":false,"rotation":0,"scale":1,"position":{"pointX":268.2500305175781,"pointY":2.11590576171875},"width":780,"sublayerTransform":[1,0,0,0,0,1,0,0,0,0,1,0,0,0,0,1],"contentsRect":{"y":0,"x":0,"width":1,"height":1},"opacity":1,"edgeAntialiasingMask":0,"height":157,"hidden":true,"anchorPoint":{"pointX":0.5,"pointY":0.5}},"texture":"D2A07172630096E6CC3E98E6E3AEDBF7"}]}]},"effects":[],"duration":0.01,"type":"buildIn","name":"apple:appear","objectID":2}],"automaticPlay":true,"hyperlinks":[],"accessibility":[{"text":"∆","targetRectangle":{"y":197.1015626192093,"x":941.8561401367188,"width":19.12400000000002,"height":33.18780517578125}},{"text":"Java_logo.png","targetRectangle":{"y":661,"x":811,"width":55.28207397460938,"height":73.41459655761719}},{"text":"scalalogo.png","targetRectangle":{"y":667.50439453125,"x":952,"width":42.36491775512695,"height":62.40580749511719}},{"text":"public class Application {","targetRectangle":{"y":114.9147138595581,"x":16,"width":266.1064453125,"height":20}},{"text":"  private String text;  ","targetRectangle":{"y":134.9147138595581,"x":16,"width":245.63671875,"height":20}},{"text":"  public static void main(String[] args) {","targetRectangle":{"y":174.9147138595581,"x":16,"width":429.8642578125,"height":20}},{"text":"    for(String str: args) {","targetRectangle":{"y":194.9147138595581,"x":16,"width":276.34130859375,"height":20}},{"text":"      System.out.println(","targetRectangle":{"y":214.9147138595581,"x":16,"width":255.87158203125,"height":20}},{"text":"\t    new Parser(str).parse());","targetRectangle":{"y":234.9147138595581,"x":16,"width":332.81103515625,"height":20}},{"text":"    }","targetRectangle":{"y":254.9147138595581,"x":16,"width":51.17431640625,"height":20}},{"text":"  }","targetRectangle":{"y":274.9147138595581,"x":16,"width":30.70458984375,"height":20}},{"text":"}","targetRectangle":{"y":294.9147138595581,"x":16,"width":10.23486328125,"height":20}},{"text":"object Application {","targetRectangle":{"y":115,"x":574,"width":204.697265625,"height":20}},{"text":"  def main(args: Array[String]): Unit = {","targetRectangle":{"y":135,"x":574,"width":419.62939453125,"height":20}},{"text":"    args.foreach { str =>","targetRectangle":{"y":155,"x":574,"width":255.87158203125,"height":20}},{"text":"      println(new Parser(str).parse)","targetRectangle":{"y":175,"x":574,"width":368.455078125,"height":20}},{"text":"    }","targetRectangle":{"y":195,"x":574,"width":51.17431640625,"height":20}},{"text":"  }","targetRectangle":{"y":215,"x":574,"width":30.70458984375,"height":20}},{"text":"}","targetRectangle":{"y":235,"x":574,"width":10.23486328125,"height":20}}],"baseLayer":{"animations":[],"initialState":{"affineTransform":[1,0,0,1,0,0],"masksToBounds":true,"rotation":0,"scale":1,"position":{"pointX":512,"pointY":384},"width":1024,"sublayerTransform":[1,0,0,0,0,1,0,0,0,0,1,0,0,0,0,1],"contentsRect":{"y":0,"x":0,"width":1,"height":1},"opacity":1,"edgeAntialiasingMask":0,"height":768,"hidden":false,"anchorPoint":{"pointX":0.5,"pointY":0.5}},"layers":[{"animations":[],"initialState":{"affineTransform":[1,0,0,1,0,0],"masksToBounds":false,"rotation":0,"scale":1,"position":{"pointX":512,"pointY":384},"width":1024,"sublayerTransform":[1,0,0,0,0,1,0,0,0,0,1,0,0,0,0,1],"contentsRect":{"y":0,"x":0,"width":1,"height":1},"opacity":1,"edgeAntialiasingMask":15,"height":768,"hidden":false,"anchorPoint":{"pointX":0.5,"pointY":0.5}},"layers":[{"animations":[],"initialState":{"affineTransform":[1,0,0,1,0,0],"masksToBounds":false,"rotation":0,"scale":1,"position":{"pointX":512,"pointY":384},"width":1024,"sublayerTransform":[1,0,0,0,0,1,0,0,0,0,1,0,0,0,0,1],"contentsRect":{"y":0,"x":0,"width":1,"height":1},"opacity":1,"edgeAntialiasingMask":15,"height":768,"hidden":false,"anchorPoint":{"pointX":0.5,"pointY":0.5}},"layers":[{"animations":[],"layers":[],"initialState":{"affineTransform":[1,0,0,1,0,0],"masksToBounds":false,"rotation":0,"scale":1,"position":{"pointX":512,"pointY":384},"width":1024,"sublayerTransform":[1,0,0,0,0,1,0,0,0,0,1,0,0,0,0,1],"contentsRect":{"y":0,"x":0,"width":1,"height":1},"opacity":1,"edgeAntialiasingMask":0,"height":768,"hidden":false,"anchorPoint":{"pointX":0.5,"pointY":0.5}},"texture":"498E23C82CA78A4BCD7BA88E5243B6FC"}]}]},{"animations":[],"initialState":{"affineTransform":[1,0,0,1,0,0],"masksToBounds":false,"rotation":0,"scale":1,"position":{"pointX":512,"pointY":384},"width":1024,"sublayerTransform":[1,0,0,0,0,1,0,0,0,0,1,0,0,0,0,1],"contentsRect":{"y":0,"x":0,"width":1,"height":1},"opacity":1,"edgeAntialiasingMask":15,"height":768,"hidden":false,"anchorPoint":{"pointX":0.5,"pointY":0.5}},"layers":[{"animations":[],"initialState":{"affineTransform":[1,0,0,1,0,0],"masksToBounds":false,"rotation":0,"scale":1,"position":{"pointX":233.1835861206055,"pointY":384.295446395874},"width":442.3671722412109,"sublayerTransform":[1,0,0,0,0,1,0,0,0,0,1,0,0,0,0,1],"contentsRect":{"y":0,"x":0,"width":1,"height":1},"opacity":1,"edgeAntialiasingMask":15,"height":746.7614650726318,"hidden":false,"anchorPoint":{"pointX":0.5,"pointY":0.5}},"layers":[{"animations":[],"layers":[],"initialState":{"affineTransform":[1,0,0,1,0,0],"masksToBounds":false,"rotation":0,"scale":1,"position":{"pointX":219,"pointY":209.5852861404419},"width":432,"sublayerTransform":[1,0,0,0,0,1,0,0,0,0,1,0,0,0,0,1],"contentsRect":{"y":0,"x":0,"width":1,"height":1},"opacity":1,"edgeAntialiasingMask":0,"height":381,"hidden":false,"anchorPoint":{"pointX":0.5,"pointY":0.5}},"texture":"970B8524056A785FC4EDB720A2EE594A"}]}]},{"animations":[],"initialState":{"affineTransform":[1,0,0,1,0,0],"masksToBounds":false,"rotation":0,"scale":1,"position":{"pointX":512,"pointY":384},"width":1024,"sublayerTransform":[1,0,0,0,0,1,0,0,0,0,1,0,0,0,0,1],"contentsRect":{"y":0,"x":0,"width":1,"height":1},"opacity":1,"edgeAntialiasingMask":15,"height":768,"hidden":false,"anchorPoint":{"pointX":0.5,"pointY":0.5}},"layers":[{"animations":[],"initialState":{"affineTransform":[1,0,0,1,0,0],"masksToBounds":false,"rotation":0,"scale":1,"position":{"pointX":879.1093778610229,"pointY":384.3807325363159},"width":618.2187557220459,"sublayerTransform":[1,0,0,0,0,1,0,0,0,0,1,0,0,0,0,1],"contentsRect":{"y":0,"x":0,"width":1,"height":1},"opacity":1,"edgeAntialiasingMask":15,"height":746.7614650726318,"hidden":false,"anchorPoint":{"pointX":0.5,"pointY":0.5}},"layers":[{"animations":[],"layers":[],"initialState":{"affineTransform":[1,0,0,1,0,0],"masksToBounds":false,"rotation":0,"scale":1,"position":{"pointX":213.5,"pointY":131},"width":421,"sublayerTransform":[1,0,0,0,0,1,0,0,0,0,1,0,0,0,0,1],"contentsRect":{"y":0,"x":0,"width":1,"height":1},"opacity":1,"edgeAntialiasingMask":0,"height":224,"hidden":false,"anchorPoint":{"pointX":0.5,"pointY":0.5}},"texture":"55F4842570F5273DFF7CDA9C7FC58DD2"}]}]},{"animations":[],"initialState":{"affineTransform":[1,0,0,1,0,0],"masksToBounds":false,"rotation":0,"scale":1,"position":{"pointX":512,"pointY":384},"width":1024,"sublayerTransform":[1,0,0,0,0,1,0,0,0,0,1,0,0,0,0,1],"contentsRect":{"y":0,"x":0,"width":1,"height":1},"opacity":1,"edgeAntialiasingMask":15,"height":768,"hidden":false,"anchorPoint":{"pointX":0.5,"pointY":0.5}},"layers":[{"animations":[],"initialState":{"affineTransform":[1,0,0,1,0,0],"masksToBounds":false,"rotation":0,"scale":1,"position":{"pointX":908.1824569702148,"pointY":697.2107162475586},"width":212.9163055419922,"sublayerTransform":[1,0,0,0,0,1,0,0,0,0,1,0,0,0,0,1],"contentsRect":{"y":0,"x":0,"width":1,"height":1},"opacity":1,"edgeAntialiasingMask":15,"height":78.42143249511719,"hidden":false,"anchorPoint":{"pointX":0.5,"pointY":0.5}},"layers":[{"animations":[],"layers":[],"initialState":{"affineTransform":[1,0,0,1,0,0],"masksToBounds":false,"rotation":0,"scale":1,"position":{"pointX":106.2756958007812,"pointY":39.5},"width":300,"sublayerTransform":[1,0,0,0,0,1,0,0,0,0,1,0,0,0,0,1],"contentsRect":{"y":0,"x":0,"width":1,"height":1},"opacity":1,"edgeAntialiasingMask":0,"height":215,"hidden":false,"anchorPoint":{"pointX":0.5,"pointY":0.5}},"texture":"AF9DC6231E46CF01E2C59626D16E1D20"}]}]},{"animations":[],"initialState":{"affineTransform":[1,0,0,1,0,0],"masksToBounds":false,"rotation":0,"scale":1,"position":{"pointX":512,"pointY":384},"width":1024,"sublayerTransform":[1,0,0,0,0,1,0,0,0,0,1,0,0,0,0,1],"contentsRect":{"y":0,"x":0,"width":1,"height":1},"opacity":1,"edgeAntialiasingMask":15,"height":768,"hidden":false,"anchorPoint":{"pointX":0.5,"pointY":0.5}},"layers":[{"animations":[],"initialState":{"affineTransform":[1,0,0,1,0,0],"masksToBounds":false,"rotation":0,"scale":1,"position":{"pointX":780.7384457588196,"pointY":185.6588627099991},"width":347.4768915176392,"sublayerTransform":[1,0,0,0,0,1,0,0,0,0,1,0,0,0,0,1],"contentsRect":{"y":0,"x":0,"width":1,"height":1},"opacity":1,"edgeAntialiasingMask":15,"height":66.01041340827942,"hidden":false,"anchorPoint":{"pointX":0.5,"pointY":0.5}},"layers":[{"animations":[],"layers":[],"initialState":{"affineTransform":[1,0,0,1,0,0],"masksToBounds":false,"rotation":0,"scale":1,"position":{"pointX":174,"pointY":32.84634399414062},"width":358,"sublayerTransform":[1,0,0,0,0,1,0,0,0,0,1,0,0,0,0,1],"contentsRect":{"y":0,"x":0,"width":1,"height":1},"opacity":1,"edgeAntialiasingMask":0,"height":81,"hidden":false,"anchorPoint":{"pointX":0.5,"pointY":0.5}},"texture":"AD4AE3662AEBEA73F5A2865D3DDEB497"}]}]},{"animations":[],"initialState":{"affineTransform":[1,0,0,1,0,0],"masksToBounds":false,"rotation":0,"scale":1,"position":{"pointX":512,"pointY":384},"width":1024,"sublayerTransform":[1,0,0,0,0,1,0,0,0,0,1,0,0,0,0,1],"contentsRect":{"y":0,"x":0,"width":1,"height":1},"opacity":1,"edgeAntialiasingMask":15,"height":768,"hidden":false,"anchorPoint":{"pointX":0.5,"pointY":0.5}},"layers":[{"animations":[],"initialState":{"affineTransform":[1,0,0,1,0,0],"masksToBounds":false,"rotation":0,"scale":1,"position":{"pointX":951.418140411377,"pointY":213.6954650878906},"width":28.12400054931641,"sublayerTransform":[1,0,0,0,0,1,0,0,0,0,1,0,0,0,0,1],"contentsRect":{"y":0,"x":0,"width":1,"height":1},"opacity":1,"edgeAntialiasingMask":15,"height":41.18780517578125,"hidden":false,"anchorPoint":{"pointX":0.5,"pointY":0.5}},"layers":[{"animations":[],"layers":[],"initialState":{"affineTransform":[1,0,0,1,0,0],"masksToBounds":false,"rotation":0,"scale":1,"position":{"pointX":17.64385986328125,"pointY":23.8984375},"width":40,"sublayerTransform":[1,0,0,0,0,1,0,0,0,0,1,0,0,0,0,1],"contentsRect":{"y":0,"x":0,"width":1,"height":1},"opacity":1,"edgeAntialiasingMask":0,"height":52,"hidden":false,"anchorPoint":{"pointX":0.5,"pointY":0.5}},"texture":"479D3FD81573DCACFC9C4BFFAFEEF9DF"}]}]},{"animations":[],"initialState":{"affineTransform":[1,0,0,1,0,0],"masksToBounds":false,"rotation":0,"scale":1,"position":{"pointX":512,"pointY":384},"width":1024,"sublayerTransform":[1,0,0,0,0,1,0,0,0,0,1,0,0,0,0,1],"contentsRect":{"y":0,"x":0,"width":1,"height":1},"opacity":1,"edgeAntialiasingMask":15,"height":768,"hidden":false,"anchorPoint":{"pointX":0.5,"pointY":0.5}},"layers":[{"animations":[],"initialState":{"affineTransform":[1,0,0,1,0,0],"masksToBounds":false,"rotation":0,"scale":1,"position":{"pointX":522.9108123779297,"pointY":572.216705083847},"width":938.3867263793945,"sublayerTransform":[1,0,0,0,0,1,0,0,0,0,1,0,0,0,0,1],"contentsRect":{"y":0,"x":0,"width":1,"height":1},"opacity":1,"edgeAntialiasingMask":15,"height":163.1922602653503,"hidden":false,"anchorPoint":{"pointX":0.5,"pointY":0.5}},"objectID":0,"layers":[{"animations":[],"layers":[],"initialState":{"affineTransform":[1,0,0,1,0,0],"masksToBounds":false,"rotation":0,"scale":1,"position":{"pointX":435.7825508117676,"pointY":27.87942504882812},"width":863,"sublayerTransform":[1,0,0,0,0,1,0,0,0,0,1,0,0,0,0,1],"contentsRect":{"y":0,"x":0,"width":1,"height":1},"opacity":1,"edgeAntialiasingMask":0,"height":43,"hidden":true,"anchorPoint":{"pointX":0.5,"pointY":0.5}},"texture":"744191A6EC4A2A68A4771BC4C40BACFE"}]}]},{"animations":[],"initialState":{"affineTransform":[1,0,0,1,0,0],"masksToBounds":false,"rotation":0,"scale":1,"position":{"pointX":512,"pointY":384},"width":1024,"sublayerTransform":[1,0,0,0,0,1,0,0,0,0,1,0,0,0,0,1],"contentsRect":{"y":0,"x":0,"width":1,"height":1},"opacity":1,"edgeAntialiasingMask":15,"height":768,"hidden":false,"anchorPoint":{"pointX":0.5,"pointY":0.5}},"layers":[{"animations":[],"initialState":{"affineTransform":[1,0,0,1,0,0],"masksToBounds":false,"rotation":0,"scale":1,"position":{"pointX":627.1002520056463,"pointY":544.3840942382812},"width":536.7005650464489,"sublayerTransform":[1,0,0,0,0,1,0,0,0,0,1,0,0,0,0,1],"contentsRect":{"y":0,"x":0,"width":1,"height":1},"opacity":1,"edgeAntialiasingMask":15,"height":4,"hidden":false,"anchorPoint":{"pointX":0.5,"pointY":0.5}},"objectID":2,"layers":[{"animations":[],"layers":[],"initialState":{"affineTransform":[1,0,0,1,0,0],"masksToBounds":false,"rotation":0,"scale":1,"position":{"pointX":268.2500305175781,"pointY":2.11590576171875},"width":780,"sublayerTransform":[1,0,0,0,0,1,0,0,0,0,1,0,0,0,0,1],"contentsRect":{"y":0,"x":0,"width":1,"height":1},"opacity":1,"edgeAntialiasingMask":0,"height":157,"hidden":true,"anchorPoint":{"pointX":0.5,"pointY":0.5}},"texture":"D2A07172630096E6CC3E98E6E3AEDBF7"}]}]},{"animations":[],"initialState":{"affineTransform":[1,0,0,1,0,0],"masksToBounds":false,"rotation":0,"scale":1,"position":{"pointX":512,"pointY":384},"width":1024,"sublayerTransform":[1,0,0,0,0,1,0,0,0,0,1,0,0,0,0,1],"contentsRect":{"y":0,"x":0,"width":1,"height":1},"opacity":1,"edgeAntialiasingMask":15,"height":768,"hidden":false,"anchorPoint":{"pointX":0.5,"pointY":0.5}},"layers":[{"animations":[],"initialState":{"affineTransform":[1,0,0,1,0,0],"masksToBounds":false,"rotation":0,"scale":1,"position":{"pointX":627.1002459526062,"pointY":554.2884517908096},"width":255.4843664169312,"sublayerTransform":[1,0,0,0,0,1,0,0,0,0,1,0,0,0,0,1],"contentsRect":{"y":0,"x":0,"width":1,"height":1},"opacity":1,"edgeAntialiasingMask":15,"height":83.46484303474426,"hidden":false,"anchorPoint":{"pointX":0.5,"pointY":0.5}},"objectID":1,"layers":[{"animations":[],"layers":[],"initialState":{"affineTransform":[1,0,0,1,0,0],"masksToBounds":false,"rotation":0,"scale":1,"position":{"pointX":108.1419372558594,"pointY":59.4439697265625},"width":211,"sublayerTransform":[1,0,0,0,0,1,0,0,0,0,1,0,0,0,0,1],"contentsRect":{"y":0,"x":0,"width":1,"height":1},"opacity":1,"edgeAntialiasingMask":0,"height":30,"hidden":true,"anchorPoint":{"pointX":0.5,"pointY":0.5}},"texture":"A3B5BAB2EB9DCC9F5C1592A17DE965BA"}]}]},{"animations":[],"initialState":{"affineTransform":[1,0,0,1,0,0],"masksToBounds":false,"rotation":0,"scale":1,"position":{"pointX":512,"pointY":384},"width":1024,"sublayerTransform":[1,0,0,0,0,1,0,0,0,0,1,0,0,0,0,1],"contentsRect":{"y":0,"x":0,"width":1,"height":1},"opacity":1,"edgeAntialiasingMask":15,"height":768,"hidden":false,"anchorPoint":{"pointX":0.5,"pointY":0.5}},"layers":[{"animations":[],"initialState":{"affineTransform":[1,0,0,1,0,0],"masksToBounds":false,"rotation":0,"scale":1,"position":{"pointX":344.9670715332031,"pointY":584.1647330082114},"width":16.80000000000001,"sublayerTransform":[1,0,0,0,0,1,0,0,0,0,1,0,0,0,0,1],"contentsRect":{"y":0,"x":0,"width":1,"height":1},"opacity":1,"edgeAntialiasingMask":15,"height":83.46484550701462,"hidden":false,"anchorPoint":{"pointX":0.5,"pointY":0.5}},"layers":[{"animations":[],"layers":[],"initialState":{"affineTransform":[1,0,0,1,0,0],"masksToBounds":false,"rotation":0,"scale":1,"position":{"pointX":8.432928466796852,"pointY":41.56768974529587},"width":20,"sublayerTransform":[1,0,0,0,0,1,0,0,0,0,1,0,0,0,0,1],"contentsRect":{"y":0,"x":0,"width":1,"height":1},"opacity":1,"edgeAntialiasingMask":0,"height":86,"hidden":true,"anchorPoint":{"pointX":0.5,"pointY":0.5}},"texture":"7197DE062BC82A94A5A6253FFB6EE085"}]}]},{"animations":[],"initialState":{"affineTransform":[1,0,0,1,0,0],"masksToBounds":false,"rotation":0,"scale":1,"position":{"pointX":512,"pointY":384},"width":1024,"sublayerTransform":[1,0,0,0,0,1,0,0,0,0,1,0,0,0,0,1],"contentsRect":{"y":0,"x":0,"width":1,"height":1},"opacity":1,"edgeAntialiasingMask":15,"height":768,"hidden":false,"anchorPoint":{"pointX":0.5,"pointY":0.5}},"layers":[{"animations":[],"initialState":{"affineTransform":[1,0,0,1,0,0],"masksToBounds":false,"rotation":0,"scale":1,"position":{"pointX":912.967041015625,"pointY":585.1647330082114},"width":16.79999999999995,"sublayerTransform":[1,0,0,0,0,1,0,0,0,0,1,0,0,0,0,1],"contentsRect":{"y":0,"x":0,"width":1,"height":1},"opacity":1,"edgeAntialiasingMask":15,"height":83.46484550701462,"hidden":false,"anchorPoint":{"pointX":0.5,"pointY":0.5}},"layers":[{"animations":[],"layers":[],"initialState":{"affineTransform":[1,0,0,1,0,0],"masksToBounds":false,"rotation":0,"scale":1,"position":{"pointX":8.432958984374977,"pointY":41.56768974529587},"width":20,"sublayerTransform":[1,0,0,0,0,1,0,0,0,0,1,0,0,0,0,1],"contentsRect":{"y":0,"x":0,"width":1,"height":1},"opacity":1,"edgeAntialiasingMask":0,"height":86,"hidden":true,"anchorPoint":{"pointX":0.5,"pointY":0.5}},"texture":"7197DE062BC82A94A5A6253FFB6EE085"}]}]},{"animations":[],"initialState":{"affineTransform":[1,0,0,1,0,0],"masksToBounds":false,"rotation":0,"scale":1,"position":{"pointX":512,"pointY":384},"width":1024,"sublayerTransform":[1,0,0,0,0,1,0,0,0,0,1,0,0,0,0,1],"contentsRect":{"y":0,"x":0,"width":1,"height":1},"opacity":1,"edgeAntialiasingMask":15,"height":768,"hidden":false,"anchorPoint":{"pointX":0.5,"pointY":0.5}},"layers":[{"animations":[],"initialState":{"affineTransform":[1,0,0,1,0,0],"masksToBounds":false,"rotation":0,"scale":1,"position":{"pointX":513.0000000886282,"pointY":164},"width":82.00000020654124,"sublayerTransform":[1,0,0,0,0,1,0,0,0,0,1,0,0,0,0,1],"contentsRect":{"y":0,"x":0,"width":1,"height":1},"opacity":1,"edgeAntialiasingMask":15,"height":31.20000007696652,"hidden":false,"anchorPoint":{"pointX":0.5,"pointY":0.5}},"layers":[{"animations":[],"layers":[],"initialState":{"affineTransform":[1,0,0,1,0,0],"masksToBounds":false,"rotation":0,"scale":1,"position":{"pointX":41.00000001464241,"pointY":15.60000003848327},"width":86,"sublayerTransform":[1,0,0,0,0,1,0,0,0,0,1,0,0,0,0,1],"contentsRect":{"y":0,"x":0,"width":1,"height":1},"opacity":1,"edgeAntialiasingMask":0,"height":34,"hidden":false,"anchorPoint":{"pointX":0.5,"pointY":0.5}},"texture":"DB106BF7A41AF014B1FD3566B1DBC04C"}]}]}]}},{"effects":[{"beginTime":0,"baseLayer":{"animations":[],"initialState":{"affineTransform":[1,0,0,1,0,0],"masksToBounds":false,"rotation":0,"scale":1,"position":{"pointX":344.9670715332031,"pointY":584.1647330082114},"width":16.80000000000001,"sublayerTransform":[1,0,0,0,0,1,0,0,0,0,1,0,0,0,0,1],"contentsRect":{"y":0,"x":0,"width":1,"height":1},"opacity":1,"edgeAntialiasingMask":15,"height":83.46484550701462,"hidden":false,"anchorPoint":{"pointX":0.5,"pointY":0.5}},"objectID":0,"layers":[{"animations":[],"initialState":{"affineTransform":[1,0,0,1,0,0],"masksToBounds":false,"rotation":0,"scale":1,"position":{"pointX":175.4329284667969,"pointY":-158.4323102547041},"width":16.80000000000001,"sublayerTransform":[1,0,0,0,0,1,0,0,0,0,1,-0.0004922987690640373,0,0,0,1],"contentsRect":{"y":0,"x":0,"width":1,"height":1},"opacity":1,"edgeAntialiasingMask":15,"height":83.46484550701462,"hidden":false,"anchorPoint":{"pointX":10.44243621826171,"pointY":-1.898192098628986}},"layers":[{"animations":[{"from":{"scalar":true},"property":"hidden","beginTime":1e-100,"to":{"scalar":false},"fillMode":"both","duration":0.01}],"layers":[],"initialState":{"affineTransform":[1,0,0,1,0,0],"masksToBounds":false,"rotation":0,"scale":1,"position":{"pointX":8.432928466796852,"pointY":41.56768974529587},"width":20,"sublayerTransform":[1,0,0,0,0,1,0,0,0,0,1,0,0,0,0,1],"contentsRect":{"y":0,"x":0,"width":1,"height":1},"opacity":1,"edgeAntialiasingMask":0,"height":86,"hidden":true,"anchorPoint":{"pointX":0.5,"pointY":0.5}},"texture":"7197DE062BC82A94A5A6253FFB6EE085"}]}]},"effects":[],"duration":0.01,"type":"buildIn","name":"apple:appear","objectID":0},{"beginTime":0,"baseLayer":{"animations":[],"initialState":{"affineTransform":[1,0,0,1,0,0],"masksToBounds":false,"rotation":0,"scale":1,"position":{"pointX":912.967041015625,"pointY":585.1647330082114},"width":16.79999999999995,"sublayerTransform":[1,0,0,0,0,1,0,0,0,0,1,0,0,0,0,1],"contentsRect":{"y":0,"x":0,"width":1,"height":1},"opacity":1,"edgeAntialiasingMask":15,"height":83.46484550701462,"hidden":false,"anchorPoint":{"pointX":0.5,"pointY":0.5}},"objectID":1,"layers":[{"animations":[],"initialState":{"affineTransform":[1,0,0,1,0,0],"masksToBounds":false,"rotation":0,"scale":1,"position":{"pointX":-392.567041015625,"pointY":-159.4323102547041},"width":16.79999999999995,"sublayerTransform":[1,0,0,0,0,1,0,0,0,0,1,-0.0004922987690640373,0,0,0,1],"contentsRect":{"y":0,"x":0,"width":1,"height":1},"opacity":1,"edgeAntialiasingMask":15,"height":83.46484550701462,"hidden":false,"anchorPoint":{"pointX":-23.36708577473965,"pointY":-1.910173190715425}},"layers":[{"animations":[{"from":{"scalar":true},"property":"hidden","beginTime":1e-100,"to":{"scalar":false},"fillMode":"both","duration":0.01}],"layers":[],"initialState":{"affineTransform":[1,0,0,1,0,0],"masksToBounds":false,"rotation":0,"scale":1,"position":{"pointX":8.432958984374977,"pointY":41.56768974529587},"width":20,"sublayerTransform":[1,0,0,0,0,1,0,0,0,0,1,0,0,0,0,1],"contentsRect":{"y":0,"x":0,"width":1,"height":1},"opacity":1,"edgeAntialiasingMask":0,"height":86,"hidden":true,"anchorPoint":{"pointX":0.5,"pointY":0.5}},"texture":"7197DE062BC82A94A5A6253FFB6EE085"}]}]},"effects":[],"duration":0.01,"type":"buildIn","name":"apple:appear","objectID":1},{"beginTime":0,"baseLayer":{"animations":[],"initialState":{"affineTransform":[1,0,0,1,0,0],"masksToBounds":false,"rotation":0,"scale":1,"position":{"pointX":780.7384457588196,"pointY":185.6588627099991},"width":347.4768915176392,"sublayerTransform":[1,0,0,0,0,1,0,0,0,0,1,0,0,0,0,1],"contentsRect":{"y":0,"x":0,"width":1,"height":1},"opacity":1,"edgeAntialiasingMask":15,"height":66.01041340827942,"hidden":false,"anchorPoint":{"pointX":0.5,"pointY":0.5}},"objectID":2,"layers":[{"animations":[],"initialState":{"affineTransform":[1,0,0,1,0,0],"masksToBounds":false,"rotation":0,"scale":1,"position":{"pointX":-95,"pointY":231.3463439941406},"width":347.4768915176392,"sublayerTransform":[1,0,0,0,0,1,0,0,0,0,1,-0.0004922987690640373,0,0,0,1],"contentsRect":{"y":0,"x":0,"width":1,"height":1},"opacity":1,"edgeAntialiasingMask":15,"height":66.01041340827942,"hidden":false,"anchorPoint":{"pointX":-0.2733994758186026,"pointY":3.504694669358392}},"layers":[{"animations":[{"animations":[{"from":{"scalar":1},"beginTime":0,"fillMode":"both","property":"opacity","duration":1.5,"timingFunction":"easeInEaseOut","to":{"scalar":0}}],"beginTime":1e-100,"fillMode":"both","duration":1.5}],"layers":[],"initialState":{"affineTransform":[1,0,0,1,0,0],"masksToBounds":false,"rotation":0,"scale":1,"position":{"pointX":174,"pointY":32.84634399414062},"width":358,"sublayerTransform":[1,0,0,0,0,1,0,0,0,0,1,0,0,0,0,1],"contentsRect":{"y":0,"x":0,"width":1,"height":1},"opacity":1,"edgeAntialiasingMask":0,"height":81,"hidden":false,"anchorPoint":{"pointX":0.5,"pointY":0.5}},"texture":"AD4AE3662AEBEA73F5A2865D3DDEB497"}]}]},"effects":[],"duration":1.5,"type":"buildOut","attributes":{"direction":0},"name":"com.apple.iWork.Keynote.Blur","objectID":2},{"beginTime":0,"baseLayer":{"animations":[],"initialState":{"affineTransform":[1,0,0,1,0,0],"masksToBounds":false,"rotation":0,"scale":1,"position":{"pointX":951.418140411377,"pointY":213.6954650878906},"width":28.12400054931641,"sublayerTransform":[1,0,0,0,0,1,0,0,0,0,1,0,0,0,0,1],"contentsRect":{"y":0,"x":0,"width":1,"height":1},"opacity":1,"edgeAntialiasingMask":15,"height":41.18780517578125,"hidden":false,"anchorPoint":{"pointX":0.5,"pointY":0.5}},"objectID":3,"layers":[{"animations":[],"initialState":{"affineTransform":[1,0,0,1,0,0],"masksToBounds":false,"rotation":0,"scale":1,"position":{"pointX":-425.3561401367188,"pointY":190.8984375},"width":28.12400054931641,"sublayerTransform":[1,0,0,0,0,1,0,0,0,0,1,-0.0004922987690640373,0,0,0,1],"contentsRect":{"y":0,"x":0,"width":1,"height":1},"opacity":1,"edgeAntialiasingMask":15,"height":41.18780517578125,"hidden":false,"anchorPoint":{"pointX":-15.12431132942278,"pointY":4.634829088010005}},"layers":[{"animations":[{"animations":[{"from":{"scalar":1},"beginTime":0,"fillMode":"both","property":"opacity","duration":1.5,"timingFunction":"easeInEaseOut","to":{"scalar":0}}],"beginTime":1e-100,"fillMode":"both","duration":1.5}],"layers":[],"initialState":{"affineTransform":[1,0,0,1,0,0],"masksToBounds":false,"rotation":0,"scale":1,"position":{"pointX":17.64385986328125,"pointY":23.8984375},"width":40,"sublayerTransform":[1,0,0,0,0,1,0,0,0,0,1,0,0,0,0,1],"contentsRect":{"y":0,"x":0,"width":1,"height":1},"opacity":1,"edgeAntialiasingMask":0,"height":52,"hidden":false,"anchorPoint":{"pointX":0.5,"pointY":0.5}},"texture":"479D3FD81573DCACFC9C4BFFAFEEF9DF"}]}]},"effects":[],"duration":1.5,"type":"buildOut","attributes":{"direction":0},"name":"com.apple.iWork.Keynote.Blur","objectID":3}],"automaticPlay":false,"hyperlinks":[],"accessibility":[{"text":"∆","targetRectangle":{"y":197.1015626192093,"x":941.8561401367188,"width":19.12400000000002,"height":33.18780517578125}},{"text":"function literal","targetRectangle":{"y":551.5560302734375,"x":503.3580627441406,"width":206.78,"height":40.02000427246094}},{"text":"Java_logo.png","targetRectangle":{"y":661,"x":811,"width":55.28207397460938,"height":73.41459655761719}},{"text":"scalalogo.png","targetRectangle":{"y":667.50439453125,"x":952,"width":42.36491775512695,"height":62.40580749511719}},{"text":"public class Application {","targetRectangle":{"y":114.9147138595581,"x":16,"width":266.1064453125,"height":20}},{"text":"  private String text;  ","targetRectangle":{"y":134.9147138595581,"x":16,"width":245.63671875,"height":20}},{"text":"  public static void main(String[] args) {","targetRectangle":{"y":174.9147138595581,"x":16,"width":429.8642578125,"height":20}},{"text":"    for(String str: args) {","targetRectangle":{"y":194.9147138595581,"x":16,"width":276.34130859375,"height":20}},{"text":"      System.out.println(","targetRectangle":{"y":214.9147138595581,"x":16,"width":255.87158203125,"height":20}},{"text":"\t    new Parser(str).parse());","targetRectangle":{"y":234.9147138595581,"x":16,"width":332.81103515625,"height":20}},{"text":"    }","targetRectangle":{"y":254.9147138595581,"x":16,"width":51.17431640625,"height":20}},{"text":"  }","targetRectangle":{"y":274.9147138595581,"x":16,"width":30.70458984375,"height":20}},{"text":"}","targetRectangle":{"y":294.9147138595581,"x":16,"width":10.23486328125,"height":20}},{"text":"args.foreach(s => new Parser(s).parse)","targetRectangle":{"y":494.6205749511719,"x":57.71744918823242,"width":869.361328125,"height":44}},{"text":"object Application {","targetRectangle":{"y":115,"x":574,"width":204.697265625,"height":20}},{"text":"  def main(args: Array[String]): Unit = {","targetRectangle":{"y":135,"x":574,"width":419.62939453125,"height":20}},{"text":"    args.foreach { str =>","targetRectangle":{"y":155,"x":574,"width":255.87158203125,"height":20}},{"text":"      println(new Parser(str).parse)","targetRectangle":{"y":175,"x":574,"width":368.455078125,"height":20}},{"text":"    }","targetRectangle":{"y":195,"x":574,"width":51.17431640625,"height":20}},{"text":"  }","targetRectangle":{"y":215,"x":574,"width":30.70458984375,"height":20}},{"text":"}","targetRectangle":{"y":235,"x":574,"width":10.23486328125,"height":20}}],"baseLayer":{"animations":[],"initialState":{"affineTransform":[1,0,0,1,0,0],"masksToBounds":true,"rotation":0,"scale":1,"position":{"pointX":512,"pointY":384},"width":1024,"sublayerTransform":[1,0,0,0,0,1,0,0,0,0,1,0,0,0,0,1],"contentsRect":{"y":0,"x":0,"width":1,"height":1},"opacity":1,"edgeAntialiasingMask":0,"height":768,"hidden":false,"anchorPoint":{"pointX":0.5,"pointY":0.5}},"layers":[{"animations":[],"initialState":{"affineTransform":[1,0,0,1,0,0],"masksToBounds":false,"rotation":0,"scale":1,"position":{"pointX":512,"pointY":384},"width":1024,"sublayerTransform":[1,0,0,0,0,1,0,0,0,0,1,0,0,0,0,1],"contentsRect":{"y":0,"x":0,"width":1,"height":1},"opacity":1,"edgeAntialiasingMask":15,"height":768,"hidden":false,"anchorPoint":{"pointX":0.5,"pointY":0.5}},"layers":[{"animations":[],"initialState":{"affineTransform":[1,0,0,1,0,0],"masksToBounds":false,"rotation":0,"scale":1,"position":{"pointX":512,"pointY":384},"width":1024,"sublayerTransform":[1,0,0,0,0,1,0,0,0,0,1,0,0,0,0,1],"contentsRect":{"y":0,"x":0,"width":1,"height":1},"opacity":1,"edgeAntialiasingMask":15,"height":768,"hidden":false,"anchorPoint":{"pointX":0.5,"pointY":0.5}},"layers":[{"animations":[],"layers":[],"initialState":{"affineTransform":[1,0,0,1,0,0],"masksToBounds":false,"rotation":0,"scale":1,"position":{"pointX":512,"pointY":384},"width":1024,"sublayerTransform":[1,0,0,0,0,1,0,0,0,0,1,0,0,0,0,1],"contentsRect":{"y":0,"x":0,"width":1,"height":1},"opacity":1,"edgeAntialiasingMask":0,"height":768,"hidden":false,"anchorPoint":{"pointX":0.5,"pointY":0.5}},"texture":"498E23C82CA78A4BCD7BA88E5243B6FC"}]}]},{"animations":[],"initialState":{"affineTransform":[1,0,0,1,0,0],"masksToBounds":false,"rotation":0,"scale":1,"position":{"pointX":512,"pointY":384},"width":1024,"sublayerTransform":[1,0,0,0,0,1,0,0,0,0,1,0,0,0,0,1],"contentsRect":{"y":0,"x":0,"width":1,"height":1},"opacity":1,"edgeAntialiasingMask":15,"height":768,"hidden":false,"anchorPoint":{"pointX":0.5,"pointY":0.5}},"layers":[{"animations":[],"initialState":{"affineTransform":[1,0,0,1,0,0],"masksToBounds":false,"rotation":0,"scale":1,"position":{"pointX":233.1835861206055,"pointY":384.295446395874},"width":442.3671722412109,"sublayerTransform":[1,0,0,0,0,1,0,0,0,0,1,0,0,0,0,1],"contentsRect":{"y":0,"x":0,"width":1,"height":1},"opacity":1,"edgeAntialiasingMask":15,"height":746.7614650726318,"hidden":false,"anchorPoint":{"pointX":0.5,"pointY":0.5}},"layers":[{"animations":[],"layers":[],"initialState":{"affineTransform":[1,0,0,1,0,0],"masksToBounds":false,"rotation":0,"scale":1,"position":{"pointX":219,"pointY":209.5852861404419},"width":432,"sublayerTransform":[1,0,0,0,0,1,0,0,0,0,1,0,0,0,0,1],"contentsRect":{"y":0,"x":0,"width":1,"height":1},"opacity":1,"edgeAntialiasingMask":0,"height":381,"hidden":false,"anchorPoint":{"pointX":0.5,"pointY":0.5}},"texture":"970B8524056A785FC4EDB720A2EE594A"}]}]},{"animations":[],"initialState":{"affineTransform":[1,0,0,1,0,0],"masksToBounds":false,"rotation":0,"scale":1,"position":{"pointX":512,"pointY":384},"width":1024,"sublayerTransform":[1,0,0,0,0,1,0,0,0,0,1,0,0,0,0,1],"contentsRect":{"y":0,"x":0,"width":1,"height":1},"opacity":1,"edgeAntialiasingMask":15,"height":768,"hidden":false,"anchorPoint":{"pointX":0.5,"pointY":0.5}},"layers":[{"animations":[],"initialState":{"affineTransform":[1,0,0,1,0,0],"masksToBounds":false,"rotation":0,"scale":1,"position":{"pointX":879.1093778610229,"pointY":384.3807325363159},"width":618.2187557220459,"sublayerTransform":[1,0,0,0,0,1,0,0,0,0,1,0,0,0,0,1],"contentsRect":{"y":0,"x":0,"width":1,"height":1},"opacity":1,"edgeAntialiasingMask":15,"height":746.7614650726318,"hidden":false,"anchorPoint":{"pointX":0.5,"pointY":0.5}},"layers":[{"animations":[],"layers":[],"initialState":{"affineTransform":[1,0,0,1,0,0],"masksToBounds":false,"rotation":0,"scale":1,"position":{"pointX":213.5,"pointY":131},"width":421,"sublayerTransform":[1,0,0,0,0,1,0,0,0,0,1,0,0,0,0,1],"contentsRect":{"y":0,"x":0,"width":1,"height":1},"opacity":1,"edgeAntialiasingMask":0,"height":224,"hidden":false,"anchorPoint":{"pointX":0.5,"pointY":0.5}},"texture":"55F4842570F5273DFF7CDA9C7FC58DD2"}]}]},{"animations":[],"initialState":{"affineTransform":[1,0,0,1,0,0],"masksToBounds":false,"rotation":0,"scale":1,"position":{"pointX":512,"pointY":384},"width":1024,"sublayerTransform":[1,0,0,0,0,1,0,0,0,0,1,0,0,0,0,1],"contentsRect":{"y":0,"x":0,"width":1,"height":1},"opacity":1,"edgeAntialiasingMask":15,"height":768,"hidden":false,"anchorPoint":{"pointX":0.5,"pointY":0.5}},"layers":[{"animations":[],"initialState":{"affineTransform":[1,0,0,1,0,0],"masksToBounds":false,"rotation":0,"scale":1,"position":{"pointX":908.1824569702148,"pointY":697.2107162475586},"width":212.9163055419922,"sublayerTransform":[1,0,0,0,0,1,0,0,0,0,1,0,0,0,0,1],"contentsRect":{"y":0,"x":0,"width":1,"height":1},"opacity":1,"edgeAntialiasingMask":15,"height":78.42143249511719,"hidden":false,"anchorPoint":{"pointX":0.5,"pointY":0.5}},"layers":[{"animations":[],"layers":[],"initialState":{"affineTransform":[1,0,0,1,0,0],"masksToBounds":false,"rotation":0,"scale":1,"position":{"pointX":106.2756958007812,"pointY":39.5},"width":300,"sublayerTransform":[1,0,0,0,0,1,0,0,0,0,1,0,0,0,0,1],"contentsRect":{"y":0,"x":0,"width":1,"height":1},"opacity":1,"edgeAntialiasingMask":0,"height":215,"hidden":false,"anchorPoint":{"pointX":0.5,"pointY":0.5}},"texture":"AF9DC6231E46CF01E2C59626D16E1D20"}]}]},{"animations":[],"initialState":{"affineTransform":[1,0,0,1,0,0],"masksToBounds":false,"rotation":0,"scale":1,"position":{"pointX":512,"pointY":384},"width":1024,"sublayerTransform":[1,0,0,0,0,1,0,0,0,0,1,0,0,0,0,1],"contentsRect":{"y":0,"x":0,"width":1,"height":1},"opacity":1,"edgeAntialiasingMask":15,"height":768,"hidden":false,"anchorPoint":{"pointX":0.5,"pointY":0.5}},"layers":[{"animations":[],"initialState":{"affineTransform":[1,0,0,1,0,0],"masksToBounds":false,"rotation":0,"scale":1,"position":{"pointX":780.7384457588196,"pointY":185.6588627099991},"width":347.4768915176392,"sublayerTransform":[1,0,0,0,0,1,0,0,0,0,1,0,0,0,0,1],"contentsRect":{"y":0,"x":0,"width":1,"height":1},"opacity":1,"edgeAntialiasingMask":15,"height":66.01041340827942,"hidden":false,"anchorPoint":{"pointX":0.5,"pointY":0.5}},"objectID":2,"layers":[{"animations":[],"layers":[],"initialState":{"affineTransform":[1,0,0,1,0,0],"masksToBounds":false,"rotation":0,"scale":1,"position":{"pointX":174,"pointY":32.84634399414062},"width":358,"sublayerTransform":[1,0,0,0,0,1,0,0,0,0,1,0,0,0,0,1],"contentsRect":{"y":0,"x":0,"width":1,"height":1},"opacity":1,"edgeAntialiasingMask":0,"height":81,"hidden":false,"anchorPoint":{"pointX":0.5,"pointY":0.5}},"texture":"AD4AE3662AEBEA73F5A2865D3DDEB497"}]}]},{"animations":[],"initialState":{"affineTransform":[1,0,0,1,0,0],"masksToBounds":false,"rotation":0,"scale":1,"position":{"pointX":512,"pointY":384},"width":1024,"sublayerTransform":[1,0,0,0,0,1,0,0,0,0,1,0,0,0,0,1],"contentsRect":{"y":0,"x":0,"width":1,"height":1},"opacity":1,"edgeAntialiasingMask":15,"height":768,"hidden":false,"anchorPoint":{"pointX":0.5,"pointY":0.5}},"layers":[{"animations":[],"initialState":{"affineTransform":[1,0,0,1,0,0],"masksToBounds":false,"rotation":0,"scale":1,"position":{"pointX":951.418140411377,"pointY":213.6954650878906},"width":28.12400054931641,"sublayerTransform":[1,0,0,0,0,1,0,0,0,0,1,0,0,0,0,1],"contentsRect":{"y":0,"x":0,"width":1,"height":1},"opacity":1,"edgeAntialiasingMask":15,"height":41.18780517578125,"hidden":false,"anchorPoint":{"pointX":0.5,"pointY":0.5}},"objectID":3,"layers":[{"animations":[],"layers":[],"initialState":{"affineTransform":[1,0,0,1,0,0],"masksToBounds":false,"rotation":0,"scale":1,"position":{"pointX":17.64385986328125,"pointY":23.8984375},"width":40,"sublayerTransform":[1,0,0,0,0,1,0,0,0,0,1,0,0,0,0,1],"contentsRect":{"y":0,"x":0,"width":1,"height":1},"opacity":1,"edgeAntialiasingMask":0,"height":52,"hidden":false,"anchorPoint":{"pointX":0.5,"pointY":0.5}},"texture":"479D3FD81573DCACFC9C4BFFAFEEF9DF"}]}]},{"animations":[],"initialState":{"affineTransform":[1,0,0,1,0,0],"masksToBounds":false,"rotation":0,"scale":1,"position":{"pointX":512,"pointY":384},"width":1024,"sublayerTransform":[1,0,0,0,0,1,0,0,0,0,1,0,0,0,0,1],"contentsRect":{"y":0,"x":0,"width":1,"height":1},"opacity":1,"edgeAntialiasingMask":15,"height":768,"hidden":false,"anchorPoint":{"pointX":0.5,"pointY":0.5}},"layers":[{"animations":[],"initialState":{"affineTransform":[1,0,0,1,0,0],"masksToBounds":false,"rotation":0,"scale":1,"position":{"pointX":522.9108123779297,"pointY":572.216705083847},"width":938.3867263793945,"sublayerTransform":[1,0,0,0,0,1,0,0,0,0,1,0,0,0,0,1],"contentsRect":{"y":0,"x":0,"width":1,"height":1},"opacity":1,"edgeAntialiasingMask":15,"height":163.1922602653503,"hidden":false,"anchorPoint":{"pointX":0.5,"pointY":0.5}},"layers":[{"animations":[],"layers":[],"initialState":{"affineTransform":[1,0,0,1,0,0],"masksToBounds":false,"rotation":0,"scale":1,"position":{"pointX":435.7825508117676,"pointY":27.87942504882812},"width":863,"sublayerTransform":[1,0,0,0,0,1,0,0,0,0,1,0,0,0,0,1],"contentsRect":{"y":0,"x":0,"width":1,"height":1},"opacity":1,"edgeAntialiasingMask":0,"height":43,"hidden":false,"anchorPoint":{"pointX":0.5,"pointY":0.5}},"texture":"744191A6EC4A2A68A4771BC4C40BACFE"}]}]},{"animations":[],"initialState":{"affineTransform":[1,0,0,1,0,0],"masksToBounds":false,"rotation":0,"scale":1,"position":{"pointX":512,"pointY":384},"width":1024,"sublayerTransform":[1,0,0,0,0,1,0,0,0,0,1,0,0,0,0,1],"contentsRect":{"y":0,"x":0,"width":1,"height":1},"opacity":1,"edgeAntialiasingMask":15,"height":768,"hidden":false,"anchorPoint":{"pointX":0.5,"pointY":0.5}},"layers":[{"animations":[],"initialState":{"affineTransform":[1,0,0,1,0,0],"masksToBounds":false,"rotation":0,"scale":1,"position":{"pointX":627.1002520056463,"pointY":544.3840942382812},"width":536.7005650464489,"sublayerTransform":[1,0,0,0,0,1,0,0,0,0,1,0,0,0,0,1],"contentsRect":{"y":0,"x":0,"width":1,"height":1},"opacity":1,"edgeAntialiasingMask":15,"height":4,"hidden":false,"anchorPoint":{"pointX":0.5,"pointY":0.5}},"layers":[{"animations":[],"layers":[],"initialState":{"affineTransform":[1,0,0,1,0,0],"masksToBounds":false,"rotation":0,"scale":1,"position":{"pointX":268.2500305175781,"pointY":2.11590576171875},"width":780,"sublayerTransform":[1,0,0,0,0,1,0,0,0,0,1,0,0,0,0,1],"contentsRect":{"y":0,"x":0,"width":1,"height":1},"opacity":1,"edgeAntialiasingMask":0,"height":157,"hidden":false,"anchorPoint":{"pointX":0.5,"pointY":0.5}},"texture":"D2A07172630096E6CC3E98E6E3AEDBF7"}]}]},{"animations":[],"initialState":{"affineTransform":[1,0,0,1,0,0],"masksToBounds":false,"rotation":0,"scale":1,"position":{"pointX":512,"pointY":384},"width":1024,"sublayerTransform":[1,0,0,0,0,1,0,0,0,0,1,0,0,0,0,1],"contentsRect":{"y":0,"x":0,"width":1,"height":1},"opacity":1,"edgeAntialiasingMask":15,"height":768,"hidden":false,"anchorPoint":{"pointX":0.5,"pointY":0.5}},"layers":[{"animations":[],"initialState":{"affineTransform":[1,0,0,1,0,0],"masksToBounds":false,"rotation":0,"scale":1,"position":{"pointX":627.1002459526062,"pointY":554.2884517908096},"width":255.4843664169312,"sublayerTransform":[1,0,0,0,0,1,0,0,0,0,1,0,0,0,0,1],"contentsRect":{"y":0,"x":0,"width":1,"height":1},"opacity":1,"edgeAntialiasingMask":15,"height":83.46484303474426,"hidden":false,"anchorPoint":{"pointX":0.5,"pointY":0.5}},"layers":[{"animations":[],"layers":[],"initialState":{"affineTransform":[1,0,0,1,0,0],"masksToBounds":false,"rotation":0,"scale":1,"position":{"pointX":108.1419372558594,"pointY":59.4439697265625},"width":211,"sublayerTransform":[1,0,0,0,0,1,0,0,0,0,1,0,0,0,0,1],"contentsRect":{"y":0,"x":0,"width":1,"height":1},"opacity":1,"edgeAntialiasingMask":0,"height":30,"hidden":false,"anchorPoint":{"pointX":0.5,"pointY":0.5}},"texture":"A3B5BAB2EB9DCC9F5C1592A17DE965BA"}]}]},{"animations":[],"initialState":{"affineTransform":[1,0,0,1,0,0],"masksToBounds":false,"rotation":0,"scale":1,"position":{"pointX":512,"pointY":384},"width":1024,"sublayerTransform":[1,0,0,0,0,1,0,0,0,0,1,0,0,0,0,1],"contentsRect":{"y":0,"x":0,"width":1,"height":1},"opacity":1,"edgeAntialiasingMask":15,"height":768,"hidden":false,"anchorPoint":{"pointX":0.5,"pointY":0.5}},"layers":[{"animations":[],"initialState":{"affineTransform":[1,0,0,1,0,0],"masksToBounds":false,"rotation":0,"scale":1,"position":{"pointX":344.9670715332031,"pointY":584.1647330082114},"width":16.80000000000001,"sublayerTransform":[1,0,0,0,0,1,0,0,0,0,1,0,0,0,0,1],"contentsRect":{"y":0,"x":0,"width":1,"height":1},"opacity":1,"edgeAntialiasingMask":15,"height":83.46484550701462,"hidden":false,"anchorPoint":{"pointX":0.5,"pointY":0.5}},"objectID":0,"layers":[{"animations":[],"layers":[],"initialState":{"affineTransform":[1,0,0,1,0,0],"masksToBounds":false,"rotation":0,"scale":1,"position":{"pointX":8.432928466796852,"pointY":41.56768974529587},"width":20,"sublayerTransform":[1,0,0,0,0,1,0,0,0,0,1,0,0,0,0,1],"contentsRect":{"y":0,"x":0,"width":1,"height":1},"opacity":1,"edgeAntialiasingMask":0,"height":86,"hidden":true,"anchorPoint":{"pointX":0.5,"pointY":0.5}},"texture":"7197DE062BC82A94A5A6253FFB6EE085"}]}]},{"animations":[],"initialState":{"affineTransform":[1,0,0,1,0,0],"masksToBounds":false,"rotation":0,"scale":1,"position":{"pointX":512,"pointY":384},"width":1024,"sublayerTransform":[1,0,0,0,0,1,0,0,0,0,1,0,0,0,0,1],"contentsRect":{"y":0,"x":0,"width":1,"height":1},"opacity":1,"edgeAntialiasingMask":15,"height":768,"hidden":false,"anchorPoint":{"pointX":0.5,"pointY":0.5}},"layers":[{"animations":[],"initialState":{"affineTransform":[1,0,0,1,0,0],"masksToBounds":false,"rotation":0,"scale":1,"position":{"pointX":912.967041015625,"pointY":585.1647330082114},"width":16.79999999999995,"sublayerTransform":[1,0,0,0,0,1,0,0,0,0,1,0,0,0,0,1],"contentsRect":{"y":0,"x":0,"width":1,"height":1},"opacity":1,"edgeAntialiasingMask":15,"height":83.46484550701462,"hidden":false,"anchorPoint":{"pointX":0.5,"pointY":0.5}},"objectID":1,"layers":[{"animations":[],"layers":[],"initialState":{"affineTransform":[1,0,0,1,0,0],"masksToBounds":false,"rotation":0,"scale":1,"position":{"pointX":8.432958984374977,"pointY":41.56768974529587},"width":20,"sublayerTransform":[1,0,0,0,0,1,0,0,0,0,1,0,0,0,0,1],"contentsRect":{"y":0,"x":0,"width":1,"height":1},"opacity":1,"edgeAntialiasingMask":0,"height":86,"hidden":true,"anchorPoint":{"pointX":0.5,"pointY":0.5}},"texture":"7197DE062BC82A94A5A6253FFB6EE085"}]}]},{"animations":[],"initialState":{"affineTransform":[1,0,0,1,0,0],"masksToBounds":false,"rotation":0,"scale":1,"position":{"pointX":512,"pointY":384},"width":1024,"sublayerTransform":[1,0,0,0,0,1,0,0,0,0,1,0,0,0,0,1],"contentsRect":{"y":0,"x":0,"width":1,"height":1},"opacity":1,"edgeAntialiasingMask":15,"height":768,"hidden":false,"anchorPoint":{"pointX":0.5,"pointY":0.5}},"layers":[{"animations":[],"initialState":{"affineTransform":[1,0,0,1,0,0],"masksToBounds":false,"rotation":0,"scale":1,"position":{"pointX":513.0000000886282,"pointY":164},"width":82.00000020654124,"sublayerTransform":[1,0,0,0,0,1,0,0,0,0,1,0,0,0,0,1],"contentsRect":{"y":0,"x":0,"width":1,"height":1},"opacity":1,"edgeAntialiasingMask":15,"height":31.20000007696652,"hidden":false,"anchorPoint":{"pointX":0.5,"pointY":0.5}},"layers":[{"animations":[],"layers":[],"initialState":{"affineTransform":[1,0,0,1,0,0],"masksToBounds":false,"rotation":0,"scale":1,"position":{"pointX":41.00000001464241,"pointY":15.60000003848327},"width":86,"sublayerTransform":[1,0,0,0,0,1,0,0,0,0,1,0,0,0,0,1],"contentsRect":{"y":0,"x":0,"width":1,"height":1},"opacity":1,"edgeAntialiasingMask":0,"height":34,"hidden":false,"anchorPoint":{"pointX":0.5,"pointY":0.5}},"texture":"DB106BF7A41AF014B1FD3566B1DBC04C"}]}]}]}},{"effects":[{"beginTime":0,"baseLayer":{"animations":[],"initialState":{"affineTransform":[1,0,0,1,0,0],"masksToBounds":false,"rotation":0,"scale":1,"position":{"pointX":344.9670715332031,"pointY":584.1647330082114},"width":16.80000000000001,"sublayerTransform":[1,0,0,0,0,1,0,0,0,0,1,0,0,0,0,1],"contentsRect":{"y":0,"x":0,"width":1,"height":1},"opacity":1,"edgeAntialiasingMask":15,"height":83.46484550701462,"hidden":false,"anchorPoint":{"pointX":0.5,"pointY":0.5}},"objectID":0,"layers":[{"animations":[],"initialState":{"affineTransform":[1,0,0,1,0,0],"masksToBounds":false,"rotation":0,"scale":1,"position":{"pointX":175.4329284667969,"pointY":-158.4323102547041},"width":16.80000000000001,"sublayerTransform":[1,0,0,0,0,1,0,0,0,0,1,-0.0004922987690640373,0,0,0,1],"contentsRect":{"y":0,"x":0,"width":1,"height":1},"opacity":1,"edgeAntialiasingMask":15,"height":83.46484550701462,"hidden":false,"anchorPoint":{"pointX":10.44243621826171,"pointY":-1.898192098628986}},"layers":[{"animations":[{"animations":[{"from":{"scalar":1},"beginTime":0,"fillMode":"both","property":"opacity","duration":1,"timingFunction":"easeInEaseOut","to":{"scalar":0}}],"beginTime":1e-100,"fillMode":"both","duration":1}],"layers":[],"initialState":{"affineTransform":[1,0,0,1,0,0],"masksToBounds":false,"rotation":0,"scale":1,"position":{"pointX":8.432928466796852,"pointY":41.56768974529587},"width":20,"sublayerTransform":[1,0,0,0,0,1,0,0,0,0,1,0,0,0,0,1],"contentsRect":{"y":0,"x":0,"width":1,"height":1},"opacity":1,"edgeAntialiasingMask":0,"height":86,"hidden":false,"anchorPoint":{"pointX":0.5,"pointY":0.5}},"texture":"7197DE062BC82A94A5A6253FFB6EE085"}]}]},"effects":[],"duration":1,"type":"buildOut","attributes":{"direction":0},"name":"com.apple.iWork.Keynote.Blur","objectID":0},{"beginTime":0,"baseLayer":{"animations":[],"initialState":{"affineTransform":[1,0,0,1,0,0],"masksToBounds":false,"rotation":0,"scale":1,"position":{"pointX":912.967041015625,"pointY":585.1647330082114},"width":16.79999999999995,"sublayerTransform":[1,0,0,0,0,1,0,0,0,0,1,0,0,0,0,1],"contentsRect":{"y":0,"x":0,"width":1,"height":1},"opacity":1,"edgeAntialiasingMask":15,"height":83.46484550701462,"hidden":false,"anchorPoint":{"pointX":0.5,"pointY":0.5}},"objectID":1,"layers":[{"animations":[],"initialState":{"affineTransform":[1,0,0,1,0,0],"masksToBounds":false,"rotation":0,"scale":1,"position":{"pointX":-392.567041015625,"pointY":-159.4323102547041},"width":16.79999999999995,"sublayerTransform":[1,0,0,0,0,1,0,0,0,0,1,-0.0004922987690640373,0,0,0,1],"contentsRect":{"y":0,"x":0,"width":1,"height":1},"opacity":1,"edgeAntialiasingMask":15,"height":83.46484550701462,"hidden":false,"anchorPoint":{"pointX":-23.36708577473965,"pointY":-1.910173190715425}},"layers":[{"animations":[{"animations":[{"from":{"scalar":1},"beginTime":0,"fillMode":"both","property":"opacity","duration":1,"timingFunction":"easeInEaseOut","to":{"scalar":0}}],"beginTime":1e-100,"fillMode":"both","duration":1}],"layers":[],"initialState":{"affineTransform":[1,0,0,1,0,0],"masksToBounds":false,"rotation":0,"scale":1,"position":{"pointX":8.432958984374977,"pointY":41.56768974529587},"width":20,"sublayerTransform":[1,0,0,0,0,1,0,0,0,0,1,0,0,0,0,1],"contentsRect":{"y":0,"x":0,"width":1,"height":1},"opacity":1,"edgeAntialiasingMask":0,"height":86,"hidden":false,"anchorPoint":{"pointX":0.5,"pointY":0.5}},"texture":"7197DE062BC82A94A5A6253FFB6EE085"}]}]},"effects":[],"duration":1,"type":"buildOut","attributes":{"direction":0},"name":"com.apple.iWork.Keynote.Blur","objectID":1}],"automaticPlay":false,"hyperlinks":[],"accessibility":[{"text":"∆","targetRectangle":{"y":197.1015626192093,"x":941.8561401367188,"width":19.12400000000002,"height":33.18780517578125}},{"text":"function literal","targetRectangle":{"y":551.5560302734375,"x":503.3580627441406,"width":206.78,"height":40.02000427246094}},{"text":"Java_logo.png","targetRectangle":{"y":661,"x":811,"width":55.28207397460938,"height":73.41459655761719}},{"text":"scalalogo.png","targetRectangle":{"y":667.50439453125,"x":952,"width":42.36491775512695,"height":62.40580749511719}},{"text":"public class Application {","targetRectangle":{"y":114.9147138595581,"x":16,"width":266.1064453125,"height":20}},{"text":"  private String text;  ","targetRectangle":{"y":134.9147138595581,"x":16,"width":245.63671875,"height":20}},{"text":"  public static void main(String[] args) {","targetRectangle":{"y":174.9147138595581,"x":16,"width":429.8642578125,"height":20}},{"text":"    for(String str: args) {","targetRectangle":{"y":194.9147138595581,"x":16,"width":276.34130859375,"height":20}},{"text":"      System.out.println(","targetRectangle":{"y":214.9147138595581,"x":16,"width":255.87158203125,"height":20}},{"text":"\t    new Parser(str).parse());","targetRectangle":{"y":234.9147138595581,"x":16,"width":332.81103515625,"height":20}},{"text":"    }","targetRectangle":{"y":254.9147138595581,"x":16,"width":51.17431640625,"height":20}},{"text":"  }","targetRectangle":{"y":274.9147138595581,"x":16,"width":30.70458984375,"height":20}},{"text":"}","targetRectangle":{"y":294.9147138595581,"x":16,"width":10.23486328125,"height":20}},{"text":"args.foreach(s => new Parser(s).parse)","targetRectangle":{"y":494.6205749511719,"x":57.71744918823242,"width":869.361328125,"height":44}},{"text":"object Application {","targetRectangle":{"y":115,"x":574,"width":204.697265625,"height":20}},{"text":"  def main(args: Array[String]): Unit = {","targetRectangle":{"y":135,"x":574,"width":419.62939453125,"height":20}},{"text":"    args.foreach { str =>","targetRectangle":{"y":155,"x":574,"width":255.87158203125,"height":20}},{"text":"      println(new Parser(str).parse)","targetRectangle":{"y":175,"x":574,"width":368.455078125,"height":20}},{"text":"    }","targetRectangle":{"y":195,"x":574,"width":51.17431640625,"height":20}},{"text":"  }","targetRectangle":{"y":215,"x":574,"width":30.70458984375,"height":20}},{"text":"}","targetRectangle":{"y":235,"x":574,"width":10.23486328125,"height":20}}],"baseLayer":{"animations":[],"initialState":{"affineTransform":[1,0,0,1,0,0],"masksToBounds":true,"rotation":0,"scale":1,"position":{"pointX":512,"pointY":384},"width":1024,"sublayerTransform":[1,0,0,0,0,1,0,0,0,0,1,0,0,0,0,1],"contentsRect":{"y":0,"x":0,"width":1,"height":1},"opacity":1,"edgeAntialiasingMask":0,"height":768,"hidden":false,"anchorPoint":{"pointX":0.5,"pointY":0.5}},"layers":[{"animations":[],"initialState":{"affineTransform":[1,0,0,1,0,0],"masksToBounds":false,"rotation":0,"scale":1,"position":{"pointX":512,"pointY":384},"width":1024,"sublayerTransform":[1,0,0,0,0,1,0,0,0,0,1,0,0,0,0,1],"contentsRect":{"y":0,"x":0,"width":1,"height":1},"opacity":1,"edgeAntialiasingMask":15,"height":768,"hidden":false,"anchorPoint":{"pointX":0.5,"pointY":0.5}},"layers":[{"animations":[],"initialState":{"affineTransform":[1,0,0,1,0,0],"masksToBounds":false,"rotation":0,"scale":1,"position":{"pointX":512,"pointY":384},"width":1024,"sublayerTransform":[1,0,0,0,0,1,0,0,0,0,1,0,0,0,0,1],"contentsRect":{"y":0,"x":0,"width":1,"height":1},"opacity":1,"edgeAntialiasingMask":15,"height":768,"hidden":false,"anchorPoint":{"pointX":0.5,"pointY":0.5}},"layers":[{"animations":[],"layers":[],"initialState":{"affineTransform":[1,0,0,1,0,0],"masksToBounds":false,"rotation":0,"scale":1,"position":{"pointX":512,"pointY":384},"width":1024,"sublayerTransform":[1,0,0,0,0,1,0,0,0,0,1,0,0,0,0,1],"contentsRect":{"y":0,"x":0,"width":1,"height":1},"opacity":1,"edgeAntialiasingMask":0,"height":768,"hidden":false,"anchorPoint":{"pointX":0.5,"pointY":0.5}},"texture":"498E23C82CA78A4BCD7BA88E5243B6FC"}]}]},{"animations":[],"initialState":{"affineTransform":[1,0,0,1,0,0],"masksToBounds":false,"rotation":0,"scale":1,"position":{"pointX":512,"pointY":384},"width":1024,"sublayerTransform":[1,0,0,0,0,1,0,0,0,0,1,0,0,0,0,1],"contentsRect":{"y":0,"x":0,"width":1,"height":1},"opacity":1,"edgeAntialiasingMask":15,"height":768,"hidden":false,"anchorPoint":{"pointX":0.5,"pointY":0.5}},"layers":[{"animations":[],"initialState":{"affineTransform":[1,0,0,1,0,0],"masksToBounds":false,"rotation":0,"scale":1,"position":{"pointX":233.1835861206055,"pointY":384.295446395874},"width":442.3671722412109,"sublayerTransform":[1,0,0,0,0,1,0,0,0,0,1,0,0,0,0,1],"contentsRect":{"y":0,"x":0,"width":1,"height":1},"opacity":1,"edgeAntialiasingMask":15,"height":746.7614650726318,"hidden":false,"anchorPoint":{"pointX":0.5,"pointY":0.5}},"layers":[{"animations":[],"layers":[],"initialState":{"affineTransform":[1,0,0,1,0,0],"masksToBounds":false,"rotation":0,"scale":1,"position":{"pointX":219,"pointY":209.5852861404419},"width":432,"sublayerTransform":[1,0,0,0,0,1,0,0,0,0,1,0,0,0,0,1],"contentsRect":{"y":0,"x":0,"width":1,"height":1},"opacity":1,"edgeAntialiasingMask":0,"height":381,"hidden":false,"anchorPoint":{"pointX":0.5,"pointY":0.5}},"texture":"970B8524056A785FC4EDB720A2EE594A"}]}]},{"animations":[],"initialState":{"affineTransform":[1,0,0,1,0,0],"masksToBounds":false,"rotation":0,"scale":1,"position":{"pointX":512,"pointY":384},"width":1024,"sublayerTransform":[1,0,0,0,0,1,0,0,0,0,1,0,0,0,0,1],"contentsRect":{"y":0,"x":0,"width":1,"height":1},"opacity":1,"edgeAntialiasingMask":15,"height":768,"hidden":false,"anchorPoint":{"pointX":0.5,"pointY":0.5}},"layers":[{"animations":[],"initialState":{"affineTransform":[1,0,0,1,0,0],"masksToBounds":false,"rotation":0,"scale":1,"position":{"pointX":879.1093778610229,"pointY":384.3807325363159},"width":618.2187557220459,"sublayerTransform":[1,0,0,0,0,1,0,0,0,0,1,0,0,0,0,1],"contentsRect":{"y":0,"x":0,"width":1,"height":1},"opacity":1,"edgeAntialiasingMask":15,"height":746.7614650726318,"hidden":false,"anchorPoint":{"pointX":0.5,"pointY":0.5}},"layers":[{"animations":[],"layers":[],"initialState":{"affineTransform":[1,0,0,1,0,0],"masksToBounds":false,"rotation":0,"scale":1,"position":{"pointX":213.5,"pointY":131},"width":421,"sublayerTransform":[1,0,0,0,0,1,0,0,0,0,1,0,0,0,0,1],"contentsRect":{"y":0,"x":0,"width":1,"height":1},"opacity":1,"edgeAntialiasingMask":0,"height":224,"hidden":false,"anchorPoint":{"pointX":0.5,"pointY":0.5}},"texture":"55F4842570F5273DFF7CDA9C7FC58DD2"}]}]},{"animations":[],"initialState":{"affineTransform":[1,0,0,1,0,0],"masksToBounds":false,"rotation":0,"scale":1,"position":{"pointX":512,"pointY":384},"width":1024,"sublayerTransform":[1,0,0,0,0,1,0,0,0,0,1,0,0,0,0,1],"contentsRect":{"y":0,"x":0,"width":1,"height":1},"opacity":1,"edgeAntialiasingMask":15,"height":768,"hidden":false,"anchorPoint":{"pointX":0.5,"pointY":0.5}},"layers":[{"animations":[],"initialState":{"affineTransform":[1,0,0,1,0,0],"masksToBounds":false,"rotation":0,"scale":1,"position":{"pointX":908.1824569702148,"pointY":697.2107162475586},"width":212.9163055419922,"sublayerTransform":[1,0,0,0,0,1,0,0,0,0,1,0,0,0,0,1],"contentsRect":{"y":0,"x":0,"width":1,"height":1},"opacity":1,"edgeAntialiasingMask":15,"height":78.42143249511719,"hidden":false,"anchorPoint":{"pointX":0.5,"pointY":0.5}},"layers":[{"animations":[],"layers":[],"initialState":{"affineTransform":[1,0,0,1,0,0],"masksToBounds":false,"rotation":0,"scale":1,"position":{"pointX":106.2756958007812,"pointY":39.5},"width":300,"sublayerTransform":[1,0,0,0,0,1,0,0,0,0,1,0,0,0,0,1],"contentsRect":{"y":0,"x":0,"width":1,"height":1},"opacity":1,"edgeAntialiasingMask":0,"height":215,"hidden":false,"anchorPoint":{"pointX":0.5,"pointY":0.5}},"texture":"AF9DC6231E46CF01E2C59626D16E1D20"}]}]},{"animations":[],"initialState":{"affineTransform":[1,0,0,1,0,0],"masksToBounds":false,"rotation":0,"scale":1,"position":{"pointX":512,"pointY":384},"width":1024,"sublayerTransform":[1,0,0,0,0,1,0,0,0,0,1,0,0,0,0,1],"contentsRect":{"y":0,"x":0,"width":1,"height":1},"opacity":1,"edgeAntialiasingMask":15,"height":768,"hidden":false,"anchorPoint":{"pointX":0.5,"pointY":0.5}},"layers":[{"animations":[],"initialState":{"affineTransform":[1,0,0,1,0,0],"masksToBounds":false,"rotation":0,"scale":1,"position":{"pointX":780.7384457588196,"pointY":185.6588627099991},"width":347.4768915176392,"sublayerTransform":[1,0,0,0,0,1,0,0,0,0,1,0,0,0,0,1],"contentsRect":{"y":0,"x":0,"width":1,"height":1},"opacity":1,"edgeAntialiasingMask":15,"height":66.01041340827942,"hidden":false,"anchorPoint":{"pointX":0.5,"pointY":0.5}},"layers":[{"animations":[],"layers":[],"initialState":{"affineTransform":[1,0,0,1,0,0],"masksToBounds":false,"rotation":0,"scale":1,"position":{"pointX":174,"pointY":32.84634399414062},"width":358,"sublayerTransform":[1,0,0,0,0,1,0,0,0,0,1,0,0,0,0,1],"contentsRect":{"y":0,"x":0,"width":1,"height":1},"opacity":1,"edgeAntialiasingMask":0,"height":81,"hidden":true,"anchorPoint":{"pointX":0.5,"pointY":0.5}},"texture":"AD4AE3662AEBEA73F5A2865D3DDEB497"}]}]},{"animations":[],"initialState":{"affineTransform":[1,0,0,1,0,0],"masksToBounds":false,"rotation":0,"scale":1,"position":{"pointX":512,"pointY":384},"width":1024,"sublayerTransform":[1,0,0,0,0,1,0,0,0,0,1,0,0,0,0,1],"contentsRect":{"y":0,"x":0,"width":1,"height":1},"opacity":1,"edgeAntialiasingMask":15,"height":768,"hidden":false,"anchorPoint":{"pointX":0.5,"pointY":0.5}},"layers":[{"animations":[],"initialState":{"affineTransform":[1,0,0,1,0,0],"masksToBounds":false,"rotation":0,"scale":1,"position":{"pointX":951.418140411377,"pointY":213.6954650878906},"width":28.12400054931641,"sublayerTransform":[1,0,0,0,0,1,0,0,0,0,1,0,0,0,0,1],"contentsRect":{"y":0,"x":0,"width":1,"height":1},"opacity":1,"edgeAntialiasingMask":15,"height":41.18780517578125,"hidden":false,"anchorPoint":{"pointX":0.5,"pointY":0.5}},"layers":[{"animations":[],"layers":[],"initialState":{"affineTransform":[1,0,0,1,0,0],"masksToBounds":false,"rotation":0,"scale":1,"position":{"pointX":17.64385986328125,"pointY":23.8984375},"width":40,"sublayerTransform":[1,0,0,0,0,1,0,0,0,0,1,0,0,0,0,1],"contentsRect":{"y":0,"x":0,"width":1,"height":1},"opacity":1,"edgeAntialiasingMask":0,"height":52,"hidden":true,"anchorPoint":{"pointX":0.5,"pointY":0.5}},"texture":"479D3FD81573DCACFC9C4BFFAFEEF9DF"}]}]},{"animations":[],"initialState":{"affineTransform":[1,0,0,1,0,0],"masksToBounds":false,"rotation":0,"scale":1,"position":{"pointX":512,"pointY":384},"width":1024,"sublayerTransform":[1,0,0,0,0,1,0,0,0,0,1,0,0,0,0,1],"contentsRect":{"y":0,"x":0,"width":1,"height":1},"opacity":1,"edgeAntialiasingMask":15,"height":768,"hidden":false,"anchorPoint":{"pointX":0.5,"pointY":0.5}},"layers":[{"animations":[],"initialState":{"affineTransform":[1,0,0,1,0,0],"masksToBounds":false,"rotation":0,"scale":1,"position":{"pointX":522.9108123779297,"pointY":572.216705083847},"width":938.3867263793945,"sublayerTransform":[1,0,0,0,0,1,0,0,0,0,1,0,0,0,0,1],"contentsRect":{"y":0,"x":0,"width":1,"height":1},"opacity":1,"edgeAntialiasingMask":15,"height":163.1922602653503,"hidden":false,"anchorPoint":{"pointX":0.5,"pointY":0.5}},"layers":[{"animations":[],"layers":[],"initialState":{"affineTransform":[1,0,0,1,0,0],"masksToBounds":false,"rotation":0,"scale":1,"position":{"pointX":435.7825508117676,"pointY":27.87942504882812},"width":863,"sublayerTransform":[1,0,0,0,0,1,0,0,0,0,1,0,0,0,0,1],"contentsRect":{"y":0,"x":0,"width":1,"height":1},"opacity":1,"edgeAntialiasingMask":0,"height":43,"hidden":false,"anchorPoint":{"pointX":0.5,"pointY":0.5}},"texture":"744191A6EC4A2A68A4771BC4C40BACFE"}]}]},{"animations":[],"initialState":{"affineTransform":[1,0,0,1,0,0],"masksToBounds":false,"rotation":0,"scale":1,"position":{"pointX":512,"pointY":384},"width":1024,"sublayerTransform":[1,0,0,0,0,1,0,0,0,0,1,0,0,0,0,1],"contentsRect":{"y":0,"x":0,"width":1,"height":1},"opacity":1,"edgeAntialiasingMask":15,"height":768,"hidden":false,"anchorPoint":{"pointX":0.5,"pointY":0.5}},"layers":[{"animations":[],"initialState":{"affineTransform":[1,0,0,1,0,0],"masksToBounds":false,"rotation":0,"scale":1,"position":{"pointX":627.1002520056463,"pointY":544.3840942382812},"width":536.7005650464489,"sublayerTransform":[1,0,0,0,0,1,0,0,0,0,1,0,0,0,0,1],"contentsRect":{"y":0,"x":0,"width":1,"height":1},"opacity":1,"edgeAntialiasingMask":15,"height":4,"hidden":false,"anchorPoint":{"pointX":0.5,"pointY":0.5}},"layers":[{"animations":[],"layers":[],"initialState":{"affineTransform":[1,0,0,1,0,0],"masksToBounds":false,"rotation":0,"scale":1,"position":{"pointX":268.2500305175781,"pointY":2.11590576171875},"width":780,"sublayerTransform":[1,0,0,0,0,1,0,0,0,0,1,0,0,0,0,1],"contentsRect":{"y":0,"x":0,"width":1,"height":1},"opacity":1,"edgeAntialiasingMask":0,"height":157,"hidden":false,"anchorPoint":{"pointX":0.5,"pointY":0.5}},"texture":"D2A07172630096E6CC3E98E6E3AEDBF7"}]}]},{"animations":[],"initialState":{"affineTransform":[1,0,0,1,0,0],"masksToBounds":false,"rotation":0,"scale":1,"position":{"pointX":512,"pointY":384},"width":1024,"sublayerTransform":[1,0,0,0,0,1,0,0,0,0,1,0,0,0,0,1],"contentsRect":{"y":0,"x":0,"width":1,"height":1},"opacity":1,"edgeAntialiasingMask":15,"height":768,"hidden":false,"anchorPoint":{"pointX":0.5,"pointY":0.5}},"layers":[{"animations":[],"initialState":{"affineTransform":[1,0,0,1,0,0],"masksToBounds":false,"rotation":0,"scale":1,"position":{"pointX":627.1002459526062,"pointY":554.2884517908096},"width":255.4843664169312,"sublayerTransform":[1,0,0,0,0,1,0,0,0,0,1,0,0,0,0,1],"contentsRect":{"y":0,"x":0,"width":1,"height":1},"opacity":1,"edgeAntialiasingMask":15,"height":83.46484303474426,"hidden":false,"anchorPoint":{"pointX":0.5,"pointY":0.5}},"layers":[{"animations":[],"layers":[],"initialState":{"affineTransform":[1,0,0,1,0,0],"masksToBounds":false,"rotation":0,"scale":1,"position":{"pointX":108.1419372558594,"pointY":59.4439697265625},"width":211,"sublayerTransform":[1,0,0,0,0,1,0,0,0,0,1,0,0,0,0,1],"contentsRect":{"y":0,"x":0,"width":1,"height":1},"opacity":1,"edgeAntialiasingMask":0,"height":30,"hidden":false,"anchorPoint":{"pointX":0.5,"pointY":0.5}},"texture":"A3B5BAB2EB9DCC9F5C1592A17DE965BA"}]}]},{"animations":[],"initialState":{"affineTransform":[1,0,0,1,0,0],"masksToBounds":false,"rotation":0,"scale":1,"position":{"pointX":512,"pointY":384},"width":1024,"sublayerTransform":[1,0,0,0,0,1,0,0,0,0,1,0,0,0,0,1],"contentsRect":{"y":0,"x":0,"width":1,"height":1},"opacity":1,"edgeAntialiasingMask":15,"height":768,"hidden":false,"anchorPoint":{"pointX":0.5,"pointY":0.5}},"layers":[{"animations":[],"initialState":{"affineTransform":[1,0,0,1,0,0],"masksToBounds":false,"rotation":0,"scale":1,"position":{"pointX":344.9670715332031,"pointY":584.1647330082114},"width":16.80000000000001,"sublayerTransform":[1,0,0,0,0,1,0,0,0,0,1,0,0,0,0,1],"contentsRect":{"y":0,"x":0,"width":1,"height":1},"opacity":1,"edgeAntialiasingMask":15,"height":83.46484550701462,"hidden":false,"anchorPoint":{"pointX":0.5,"pointY":0.5}},"objectID":0,"layers":[{"animations":[],"layers":[],"initialState":{"affineTransform":[1,0,0,1,0,0],"masksToBounds":false,"rotation":0,"scale":1,"position":{"pointX":8.432928466796852,"pointY":41.56768974529587},"width":20,"sublayerTransform":[1,0,0,0,0,1,0,0,0,0,1,0,0,0,0,1],"contentsRect":{"y":0,"x":0,"width":1,"height":1},"opacity":1,"edgeAntialiasingMask":0,"height":86,"hidden":false,"anchorPoint":{"pointX":0.5,"pointY":0.5}},"texture":"7197DE062BC82A94A5A6253FFB6EE085"}]}]},{"animations":[],"initialState":{"affineTransform":[1,0,0,1,0,0],"masksToBounds":false,"rotation":0,"scale":1,"position":{"pointX":512,"pointY":384},"width":1024,"sublayerTransform":[1,0,0,0,0,1,0,0,0,0,1,0,0,0,0,1],"contentsRect":{"y":0,"x":0,"width":1,"height":1},"opacity":1,"edgeAntialiasingMask":15,"height":768,"hidden":false,"anchorPoint":{"pointX":0.5,"pointY":0.5}},"layers":[{"animations":[],"initialState":{"affineTransform":[1,0,0,1,0,0],"masksToBounds":false,"rotation":0,"scale":1,"position":{"pointX":912.967041015625,"pointY":585.1647330082114},"width":16.79999999999995,"sublayerTransform":[1,0,0,0,0,1,0,0,0,0,1,0,0,0,0,1],"contentsRect":{"y":0,"x":0,"width":1,"height":1},"opacity":1,"edgeAntialiasingMask":15,"height":83.46484550701462,"hidden":false,"anchorPoint":{"pointX":0.5,"pointY":0.5}},"objectID":1,"layers":[{"animations":[],"layers":[],"initialState":{"affineTransform":[1,0,0,1,0,0],"masksToBounds":false,"rotation":0,"scale":1,"position":{"pointX":8.432958984374977,"pointY":41.56768974529587},"width":20,"sublayerTransform":[1,0,0,0,0,1,0,0,0,0,1,0,0,0,0,1],"contentsRect":{"y":0,"x":0,"width":1,"height":1},"opacity":1,"edgeAntialiasingMask":0,"height":86,"hidden":false,"anchorPoint":{"pointX":0.5,"pointY":0.5}},"texture":"7197DE062BC82A94A5A6253FFB6EE085"}]}]},{"animations":[],"initialState":{"affineTransform":[1,0,0,1,0,0],"masksToBounds":false,"rotation":0,"scale":1,"position":{"pointX":512,"pointY":384},"width":1024,"sublayerTransform":[1,0,0,0,0,1,0,0,0,0,1,0,0,0,0,1],"contentsRect":{"y":0,"x":0,"width":1,"height":1},"opacity":1,"edgeAntialiasingMask":15,"height":768,"hidden":false,"anchorPoint":{"pointX":0.5,"pointY":0.5}},"layers":[{"animations":[],"initialState":{"affineTransform":[1,0,0,1,0,0],"masksToBounds":false,"rotation":0,"scale":1,"position":{"pointX":513.0000000886282,"pointY":164},"width":82.00000020654124,"sublayerTransform":[1,0,0,0,0,1,0,0,0,0,1,0,0,0,0,1],"contentsRect":{"y":0,"x":0,"width":1,"height":1},"opacity":1,"edgeAntialiasingMask":15,"height":31.20000007696652,"hidden":false,"anchorPoint":{"pointX":0.5,"pointY":0.5}},"layers":[{"animations":[],"layers":[],"initialState":{"affineTransform":[1,0,0,1,0,0],"masksToBounds":false,"rotation":0,"scale":1,"position":{"pointX":41.00000001464241,"pointY":15.60000003848327},"width":86,"sublayerTransform":[1,0,0,0,0,1,0,0,0,0,1,0,0,0,0,1],"contentsRect":{"y":0,"x":0,"width":1,"height":1},"opacity":1,"edgeAntialiasingMask":0,"height":34,"hidden":false,"anchorPoint":{"pointX":0.5,"pointY":0.5}},"texture":"DB106BF7A41AF014B1FD3566B1DBC04C"}]}]}]}},{"effects":[{"beginTime":0,"baseLayer":{"animations":[],"initialState":{"affineTransform":[1,0,0,1,0,0],"masksToBounds":true,"rotation":0,"scale":1,"position":{"pointX":512,"pointY":384},"width":1024,"sublayerTransform":[1,0,0,0,0,1,0,0,0,0,1,0,0,0,0,1],"contentsRect":{"y":0,"x":0,"width":1,"height":1},"opacity":1,"edgeAntialiasingMask":0,"height":768,"hidden":false,"anchorPoint":{"pointX":0.5,"pointY":0.5}},"objectID":0,"layers":[{"animations":[],"initialState":{"affineTransform":[1,0,0,1,0,0],"masksToBounds":false,"rotation":0,"scale":1,"position":{"pointX":512,"pointY":384},"width":1024,"sublayerTransform":[1,0,0,0,0,1,0,0,0,0,1,-0.0004922987690640373,0,0,0,1],"contentsRect":{"y":0,"x":0,"width":1,"height":1},"opacity":1,"edgeAntialiasingMask":15,"height":768,"hidden":false,"anchorPoint":{"pointX":0.5,"pointY":0.5}},"layers":[{"animations":[],"layers":[],"initialState":{"affineTransform":[1,0,0,1,0,0],"masksToBounds":false,"rotation":0,"scale":1,"position":{"pointX":512,"pointY":384},"width":1024,"sublayerTransform":[1,0,0,0,0,1,0,0,0,0,1,0,0,0,0,1],"contentsRect":{"y":0,"x":0,"width":1,"height":1},"opacity":1,"edgeAntialiasingMask":0,"height":768,"hidden":false,"anchorPoint":{"pointX":0.5,"pointY":0.5}},"texture":"5BBC8E21AC430EC8AE55EF4FC9B26599"},{"animations":[{"from":{"scalar":false},"property":"hidden","beginTime":0,"to":{"scalar":true},"fillMode":"both","duration":0.01}],"layers":[],"initialState":{"affineTransform":[1,0,0,1,0,0],"masksToBounds":false,"rotation":0,"scale":1,"position":{"pointX":512,"pointY":384},"width":1024,"sublayerTransform":[1,0,0,0,0,1,0,0,0,0,1,0,0,0,0,1],"contentsRect":{"y":0,"x":0,"width":1,"height":1},"opacity":1,"edgeAntialiasingMask":0,"height":768,"hidden":false,"anchorPoint":{"pointX":0.5,"pointY":0.5}},"texture":"4055A0845993B381E0E64EA4B82BF601"}]}]},"effects":[],"duration":0.01,"type":"transition","name":"none","objectID":0}],"automaticPlay":false,"hyperlinks":[],"accessibility":[{"text":"∆","targetRectangle":{"y":197.1015626192093,"x":941.8561401367188,"width":19.12400000000002,"height":33.18780517578125}},{"text":"function literal","targetRectangle":{"y":551.5560302734375,"x":503.3580627441406,"width":206.78,"height":40.02000427246094}},{"text":"Java_logo.png","targetRectangle":{"y":661,"x":811,"width":55.28207397460938,"height":73.41459655761719}},{"text":"scalalogo.png","targetRectangle":{"y":667.50439453125,"x":952,"width":42.36491775512695,"height":62.40580749511719}},{"text":"public class Application {","targetRectangle":{"y":114.9147138595581,"x":16,"width":266.1064453125,"height":20}},{"text":"  private String text;  ","targetRectangle":{"y":134.9147138595581,"x":16,"width":245.63671875,"height":20}},{"text":"  public static void main(String[] args) {","targetRectangle":{"y":174.9147138595581,"x":16,"width":429.8642578125,"height":20}},{"text":"    for(String str: args) {","targetRectangle":{"y":194.9147138595581,"x":16,"width":276.34130859375,"height":20}},{"text":"      System.out.println(","targetRectangle":{"y":214.9147138595581,"x":16,"width":255.87158203125,"height":20}},{"text":"\t    new Parser(str).parse());","targetRectangle":{"y":234.9147138595581,"x":16,"width":332.81103515625,"height":20}},{"text":"    }","targetRectangle":{"y":254.9147138595581,"x":16,"width":51.17431640625,"height":20}},{"text":"  }","targetRectangle":{"y":274.9147138595581,"x":16,"width":30.70458984375,"height":20}},{"text":"}","targetRectangle":{"y":294.9147138595581,"x":16,"width":10.23486328125,"height":20}},{"text":"args.foreach(s => new Parser(s).parse)","targetRectangle":{"y":494.6205749511719,"x":57.71744918823242,"width":869.361328125,"height":44}},{"text":"object Application {","targetRectangle":{"y":115,"x":574,"width":204.697265625,"height":20}},{"text":"  def main(args: Array[String]): Unit = {","targetRectangle":{"y":135,"x":574,"width":419.62939453125,"height":20}},{"text":"    args.foreach { str =>","targetRectangle":{"y":155,"x":574,"width":255.87158203125,"height":20}},{"text":"      println(new Parser(str).parse)","targetRectangle":{"y":175,"x":574,"width":368.455078125,"height":20}},{"text":"    }","targetRectangle":{"y":195,"x":574,"width":51.17431640625,"height":20}},{"text":"  }","targetRectangle":{"y":215,"x":574,"width":30.70458984375,"height":20}},{"text":"}","targetRectangle":{"y":235,"x":574,"width":10.23486328125,"height":20}}],"baseLayer":{"animations":[],"initialState":{"affineTransform":[1,0,0,1,0,0],"masksToBounds":true,"rotation":0,"scale":1,"position":{"pointX":512,"pointY":384},"width":1024,"sublayerTransform":[1,0,0,0,0,1,0,0,0,0,1,0,0,0,0,1],"contentsRect":{"y":0,"x":0,"width":1,"height":1},"opacity":1,"edgeAntialiasingMask":0,"height":768,"hidden":false,"anchorPoint":{"pointX":0.5,"pointY":0.5}},"objectID":0,"layers":[{"animations":[],"initialState":{"affineTransform":[1,0,0,1,0,0],"masksToBounds":false,"rotation":0,"scale":1,"position":{"pointX":512,"pointY":384},"width":1024,"sublayerTransform":[1,0,0,0,0,1,0,0,0,0,1,-0.0004922987690640373,0,0,0,1],"contentsRect":{"y":0,"x":0,"width":1,"height":1},"opacity":1,"edgeAntialiasingMask":15,"height":768,"hidden":false,"anchorPoint":{"pointX":0.5,"pointY":0.5}},"layers":[{"animations":[],"layers":[],"initialState":{"affineTransform":[1,0,0,1,0,0],"masksToBounds":false,"rotation":0,"scale":1,"position":{"pointX":512,"pointY":384},"width":1024,"sublayerTransform":[1,0,0,0,0,1,0,0,0,0,1,0,0,0,0,1],"contentsRect":{"y":0,"x":0,"width":1,"height":1},"opacity":1,"edgeAntialiasingMask":0,"height":768,"hidden":false,"anchorPoint":{"pointX":0.5,"pointY":0.5}},"texture":"5BBC8E21AC430EC8AE55EF4FC9B26599"},{"animations":[{"from":{"scalar":false},"property":"hidden","beginTime":0,"to":{"scalar":true},"fillMode":"both","duration":0.01}],"layers":[],"initialState":{"affineTransform":[1,0,0,1,0,0],"masksToBounds":false,"rotation":0,"scale":1,"position":{"pointX":512,"pointY":384},"width":1024,"sublayerTransform":[1,0,0,0,0,1,0,0,0,0,1,0,0,0,0,1],"contentsRect":{"y":0,"x":0,"width":1,"height":1},"opacity":1,"edgeAntialiasingMask":0,"height":768,"hidden":false,"anchorPoint":{"pointX":0.5,"pointY":0.5}},"texture":"4055A0845993B381E0E64EA4B82BF601"}]}]}}]}